{"nT3E2EORXiaX2aAvUIsVBg": {"id": "nT3E2EORXiaX2aAvUIsVBg", "alias": "swel-seattle", "name": "SWeL", "image_url": "https://s3-media4.fl.yelpcdn.com/bphoto/MGZUkSgksayiX6f9bZ-w5w/o.jpg", "is_claimed": true, "is_closed": false, "url": "https://www.yelp.com/biz/swel-seattle?adjust_creative=6dT2LEKGFHkdpZhE3GbcSQ&utm_campaign=yelp_api_v3&utm_medium=api_v3_business_lookup&utm_source=6dT2LEKGFHkdpZhE3GbcSQ", "phone": "+12064589815", "display_phone": "(206) 458-9815", "review_count": 108, "categories": [{"alias": "newamerican", "title": "American (New)"}], "rating": 4.5, "location": {"address1": "3417 Evanston Ave N", "address2": "Ste 104", "address3": null, "city": "Seattle", "zip_code": "98103", "country": "US", "state": "WA", "display_address": ["3417 Evanston Ave N", "Ste 104", "Seattle, WA 98103"], "cross_streets": "35th St & 34th St"}, "coordinates": {"latitude": 47.6506497158479, "longitude": -122.351646939039}, "photos": ["https://s3-media4.fl.yelpcdn.com/bphoto/MGZUkSgksayiX6f9bZ-w5w/o.jpg", "https://s3-media2.fl.yelpcdn.com/bphoto/0WSNdqZg0hsj8jwutdJFVA/o.jpg", "https://s3-media3.fl.yelpcdn.com/bphoto/YmSSIxgXTgC2dclFpx1BYw/o.jpg"], "price": "$$", "hours": [{"open": [{"is_overnight": false, "start": "1600", "end": "2200", "day": 0}, {"is_overnight": false, "start": "1600", "end": "2200", "day": 1}, {"is_overnight": false, "start": "1600", "end": "2200", "day": 2}, {"is_overnight": false, "start": "1600", "end": "2200", "day": 3}, {"is_overnight": false, "start": "1600", "end": "2300", "day": 4}, {"is_overnight": false, "start": "1600", "end": "2300", "day": 5}, {"is_overnight": false, "start": "1600", "end": "2200", "day": 6}], "hours_type": "REGULAR", "is_open_now": false}], "transactions": []}, "VOPdG8llLPaga9iJxXcMuQ": {"id": "VOPdG8llLPaga9iJxXcMuQ", "alias": "the-pink-door-seattle-4", "name": "The Pink Door", "image_url": "https://s3-media3.fl.yelpcdn.com/bphoto/4MmMuSGEQCXpqEoCOhL7tw/o.jpg", "is_claimed": true, "is_closed": false, "url": "https://www.yelp.com/biz/the-pink-door-seattle-4?adjust_creative=6dT2LEKGFHkdpZhE3GbcSQ&utm_campaign=yelp_api_v3&utm_medium=api_v3_business_lookup&utm_source=6dT2LEKGFHkdpZhE3GbcSQ", "phone": "+12064433241", "display_phone": "(206) 443-3241", "review_count": 3303, "categories": [{"alias": "italian", "title": "Italian"}, {"alias": "wine_bars", "title": "Wine Bars"}, {"alias": "gluten_free", "title": "Gluten-Free"}], "rating": 4.5, "location": {"address1": "1919 Post Alley", "address2": "", "address3": "", "city": "Seattle", "zip_code": "98101", "country": "US", "state": "WA", "display_address": ["1919 Post Alley", "Seattle, WA 98101"], "cross_streets": "Virginia St & Stewart St"}, "coordinates": {"latitude": 47.61028, "longitude": -122.3425}, "photos": ["https://s3-media3.fl.yelpcdn.com/bphoto/4MmMuSGEQCXpqEoCOhL7tw/o.jpg", "https://s3-media3.fl.yelpcdn.com/bphoto/ILI5ZvXxKKyWMcet9ddbiA/o.jpg", "https://s3-media4.fl.yelpcdn.com/bphoto/UvX8wZTqsIZQutnz7Qz4Lg/o.jpg"], "price": "$$", "hours": [{"open": [{"is_overnight": false, "start": "1130", "end": "2330", "day": 0}, {"is_overnight": false, "start": "1130", "end": "2330", "day": 1}, {"is_overnight": false, "start": "1130", "end": "2330", "day": 2}, {"is_overnight": false, "start": "1130", "end": "2330", "day": 3}, {"is_overnight": true, "start": "1130", "end": "0100", "day": 4}, {"is_overnight": true, "start": "1130", "end": "0100", "day": 5}, {"is_overnight": false, "start": "1600", "end": "2200", "day": 6}], "hours_type": "REGULAR", "is_open_now": false}], "transactions": []}, "ps9ZlLoLYTfK87IjW9REfg": {"id": "ps9ZlLoLYTfK87IjW9REfg", "alias": "radiator-whiskey-seattle", "name": "Radiator Whiskey", "image_url": "https://s3-media2.fl.yelpcdn.com/bphoto/A3x035N72PjqAQ7MIf2kAQ/o.jpg", "is_claimed": true, "is_closed": false, "url": "https://www.yelp.com/biz/radiator-whiskey-seattle?adjust_creative=6dT2LEKGFHkdpZhE3GbcSQ&utm_campaign=yelp_api_v3&utm_medium=api_v3_business_lookup&utm_source=6dT2LEKGFHkdpZhE3GbcSQ", "phone": "+12064674268", "display_phone": "(206) 467-4268", "review_count": 985, "categories": [{"alias": "newamerican", "title": "American (New)"}, {"alias": "cocktailbars", "title": "Cocktail Bars"}], "rating": 4.5, "location": {"address1": "94 Pike St", "address2": "Ste 30", "address3": "", "city": "Seattle", "zip_code": "98101", "country": "US", "state": "WA", "display_address": ["94 Pike St", "Ste 30", "Seattle, WA 98101"], "cross_streets": "Post Aly & 1st Ave"}, "coordinates": {"latitude": 47.60888, "longitude": -122.34036}, "photos": ["https://s3-media2.fl.yelpcdn.com/bphoto/A3x035N72PjqAQ7MIf2kAQ/o.jpg", "https://s3-media4.fl.yelpcdn.com/bphoto/nwj8sHoUmPlb1OAxiGSyBQ/o.jpg", "https://s3-media1.fl.yelpcdn.com/bphoto/nmd8aNsYCyD6QHNMcTtgYg/o.jpg"], "price": "$$", "hours": [{"open": [{"is_overnight": false, "start": "1600", "end": "0000", "day": 0}, {"is_overnight": false, "start": "1600", "end": "0000", "day": 1}, {"is_overnight": false, "start": "1600", "end": "0000", "day": 2}, {"is_overnight": false, "start": "1600", "end": "0000", "day": 3}, {"is_overnight": false, "start": "1600", "end": "0000", "day": 4}, {"is_overnight": false, "start": "1600", "end": "0000", "day": 5}], "hours_type": "REGULAR", "is_open_now": false}], "transactions": ["restaurant_reservation"]}, "GrFxdNfPvdlVrueRY7XERg": {"id": "GrFxdNfPvdlVrueRY7XERg", "alias": "list-seattle", "name": "List", "image_url": "https://s3-media1.fl.yelpcdn.com/bphoto/1SAsDex924II8SouZwGzAw/o.jpg", "is_claimed": true, "is_closed": false, "url": "https://www.yelp.com/biz/list-seattle?adjust_creative=6dT2LEKGFHkdpZhE3GbcSQ&utm_campaign=yelp_api_v3&utm_medium=api_v3_business_lookup&utm_source=6dT2LEKGFHkdpZhE3GbcSQ", "phone": "+12064411000", "display_phone": "(206) 441-1000", "review_count": 1509, "categories": [{"alias": "italian", "title": "Italian"}, {"alias": "tapasmallplates", "title": "Tapas/Small Plates"}, {"alias": "cocktailbars", "title": "Cocktail Bars"}], "rating": 4.5, "location": {"address1": "2226 1st Ave", "address2": "", "address3": "", "city": "Seattle", "zip_code": "98121", "country": "US", "state": "WA", "display_address": ["2226 1st Ave", "Seattle, WA 98121"], "cross_streets": "Bell St & Blanchard St"}, "coordinates": {"latitude": 47.61334, "longitude": -122.34587}, "photos": ["https://s3-media1.fl.yelpcdn.com/bphoto/1SAsDex924II8SouZwGzAw/o.jpg", "https://s3-media2.fl.yelpcdn.com/bphoto/uxoKwXkExh46601e9McG0A/o.jpg", "https://s3-media4.fl.yelpcdn.com/bphoto/WD0WX7bj-ATUj9L9DlnMIQ/o.jpg"], "price": "$$", "hours": [{"open": [{"is_overnight": false, "start": "1600", "end": "0000", "day": 0}, {"is_overnight": false, "start": "1600", "end": "0000", "day": 1}, {"is_overnight": false, "start": "1600", "end": "0000", "day": 2}, {"is_overnight": false, "start": "1600", "end": "0000", "day": 3}, {"is_overnight": false, "start": "1600", "end": "0000", "day": 4}, {"is_overnight": false, "start": "1600", "end": "0000", "day": 5}, {"is_overnight": false, "start": "1600", "end": "0000", "day": 6}], "hours_type": "REGULAR", "is_open_now": false}], "transactions": []}, "h1Q0Wkx5TUUZeVjJrXTwmQ": {"id": "h1Q0Wkx5TUUZeVjJrXTwmQ", "alias": "chan-seattle-seattle-2", "name": "Chan Seattle", "image_url": "https://s3-media4.fl.yelpcdn.com/bphoto/GW_ZhVgN9AFy6R7uJwB8Ig/o.jpg", "is_claimed": true, "is_closed": false, "url": "https://www.yelp.com/biz/chan-seattle-seattle-2?adjust_creative=6dT2LEKGFHkdpZhE3GbcSQ&utm_campaign=yelp_api_v3&utm_medium=api_v3_business_lookup&utm_source=6dT2LEKGFHkdpZhE3GbcSQ", "phone": "+12064435443", "display_phone": "(206) 443-5443", "review_count": 687, "categories": [{"alias": "asianfusion", "title": "Asian Fusion"}, {"alias": "korean", "title": "Korean"}, {"alias": "gastropubs", "title": "Gastropubs"}], "rating": 4.5, "location": {"address1": "86 Pine St", "address2": "", "address3": "", "city": "Seattle", "zip_code": "98101", "country": "US", "state": "WA", "display_address": ["86 Pine St", "Seattle, WA 98101"], "cross_streets": "Pike Pl & Post Aly"}, "coordinates": {"latitude": 47.6098823547363, "longitude": -122.341438293457}, "photos": ["https://s3-media4.fl.yelpcdn.com/bphoto/GW_ZhVgN9AFy6R7uJwB8Ig/o.jpg", "https://s3-media1.fl.yelpcdn.com/bphoto/_RDJknM3_qeLI4_Q1x4teg/o.jpg", "https://s3-media2.fl.yelpcdn.com/bphoto/_VSDGOe0_Ji5Fe3UftUx0A/o.jpg"], "price": "$$", "hours": [{"open": [{"is_overnight": false, "start": "1700", "end": "2200", "day": 1}, {"is_overnight": false, "start": "1700", "end": "2200", "day": 2}, {"is_overnight": false, "start": "1700", "end": "2200", "day": 3}, {"is_overnight": false, "start": "1700", "end": "2200", "day": 4}, {"is_overnight": false, "start": "1700", "end": "2200", "day": 5}], "hours_type": "REGULAR", "is_open_now": false}], "transactions": []}, "BLVe8EsrRKphA8Ivxuavmw": {"id": "BLVe8EsrRKphA8Ivxuavmw", "alias": "black-bottle-seattle-2", "name": "Black Bottle", "image_url": "https://s3-media4.fl.yelpcdn.com/bphoto/H9zEzoSse6ieIGIUw6Xr-Q/o.jpg", "is_claimed": true, "is_closed": false, "url": "https://www.yelp.com/biz/black-bottle-seattle-2?adjust_creative=6dT2LEKGFHkdpZhE3GbcSQ&utm_campaign=yelp_api_v3&utm_medium=api_v3_business_lookup&utm_source=6dT2LEKGFHkdpZhE3GbcSQ", "phone": "+12064411500", "display_phone": "(206) 441-1500", "review_count": 1022, "categories": [{"alias": "newamerican", "title": "American (New)"}, {"alias": "gastropubs", "title": "Gastropubs"}, {"alias": "tapasmallplates", "title": "Tapas/Small Plates"}], "rating": 4.0, "location": {"address1": "2600 1st Ave", "address2": "", "address3": "", "city": "Seattle", "zip_code": "98121", "country": "US", "state": "WA", "display_address": ["2600 1st Ave", "Seattle, WA 98121"], "cross_streets": "Cedar St & Vine St"}, "coordinates": {"latitude": 47.61543, "longitude": -122.34967}, "photos": ["https://s3-media4.fl.yelpcdn.com/bphoto/H9zEzoSse6ieIGIUw6Xr-Q/o.jpg", "https://s3-media3.fl.yelpcdn.com/bphoto/Xfj3JmtcpWbVWAXKGt-JJQ/o.jpg", "https://s3-media2.fl.yelpcdn.com/bphoto/8YG01qzcO_1GXA2-SX-AyA/o.jpg"], "price": "$$", "hours": [{"open": [{"is_overnight": false, "start": "1600", "end": "0000", "day": 0}, {"is_overnight": false, "start": "1600", "end": "0000", "day": 1}, {"is_overnight": false, "start": "1600", "end": "0000", "day": 2}, {"is_overnight": false, "start": "1600", "end": "0000", "day": 3}, {"is_overnight": true, "start": "1600", "end": "0200", "day": 4}, {"is_overnight": true, "start": "1600", "end": "0200", "day": 5}, {"is_overnight": false, "start": "1600", "end": "0000", "day": 6}], "hours_type": "REGULAR", "is_open_now": false}], "transactions": []}, "r2qcG59sAqqptnwL4aJGhg": {"id": "r2qcG59sAqqptnwL4aJGhg", "alias": "toulouse-petit-kitchen-and-lounge-seattle", "name": "Toulouse Petit Kitchen & Lounge", "image_url": "https://s3-media1.fl.yelpcdn.com/bphoto/UmEDw1vIvHMNagxlZspJ9A/o.jpg", "is_claimed": true, "is_closed": false, "url": "https://www.yelp.com/biz/toulouse-petit-kitchen-and-lounge-seattle?adjust_creative=6dT2LEKGFHkdpZhE3GbcSQ&utm_campaign=yelp_api_v3&utm_medium=api_v3_business_lookup&utm_source=6dT2LEKGFHkdpZhE3GbcSQ", "phone": "+12064329069", "display_phone": "(206) 432-9069", "review_count": 3346, "categories": [{"alias": "cajun", "title": "Cajun/Creole"}, {"alias": "bars", "title": "Bars"}], "rating": 4.0, "location": {"address1": "601 Queen Anne Ave N", "address2": "", "address3": "", "city": "Seattle", "zip_code": "98109", "country": "US", "state": "WA", "display_address": ["601 Queen Anne Ave N", "Seattle, WA 98109"], "cross_streets": "Roy St & Mercer St"}, "coordinates": {"latitude": 47.624851, "longitude": -122.357127}, "photos": ["https://s3-media1.fl.yelpcdn.com/bphoto/UmEDw1vIvHMNagxlZspJ9A/o.jpg", "https://s3-media2.fl.yelpcdn.com/bphoto/-n80cccbKIuSBT6ZzUJVyQ/o.jpg", "https://s3-media2.fl.yelpcdn.com/bphoto/4Mnp69RSXK_5cN8S_MAwgA/o.jpg"], "price": "$$", "hours": [{"open": [{"is_overnight": true, "start": "0900", "end": "0200", "day": 0}, {"is_overnight": true, "start": "0900", "end": "0200", "day": 1}, {"is_overnight": true, "start": "0900", "end": "0200", "day": 2}, {"is_overnight": true, "start": "0900", "end": "0200", "day": 3}, {"is_overnight": true, "start": "0900", "end": "0200", "day": 4}, {"is_overnight": true, "start": "0800", "end": "0200", "day": 5}, {"is_overnight": true, "start": "0800", "end": "0200", "day": 6}], "hours_type": "REGULAR", "is_open_now": true}], "transactions": []}, "XE0C4z-DByNlXZ2IUtouhA": {"id": "XE0C4z-DByNlXZ2IUtouhA", "alias": "reckless-noodle-house-seattle-2", "name": "Reckless Noodle House", "image_url": "https://s3-media1.fl.yelpcdn.com/bphoto/HfXBi87gY7gih195TNBbJg/o.jpg", "is_claimed": true, "is_closed": false, "url": "https://www.yelp.com/biz/reckless-noodle-house-seattle-2?adjust_creative=6dT2LEKGFHkdpZhE3GbcSQ&utm_campaign=yelp_api_v3&utm_medium=api_v3_business_lookup&utm_source=6dT2LEKGFHkdpZhE3GbcSQ", "phone": "+12063295499", "display_phone": "(206) 329-5499", "review_count": 46, "categories": [{"alias": "bars", "title": "Bars"}, {"alias": "noodles", "title": "Noodles"}], "rating": 4.5, "location": {"address1": "2519 S Jackson St", "address2": "", "address3": null, "city": "Seattle", "zip_code": "98144", "country": "US", "state": "WA", "display_address": ["2519 S Jackson St", "Seattle, WA 98144"], "cross_streets": "S 26th Ave & S 25th Ave"}, "coordinates": {"latitude": 47.5991, "longitude": -122.29906}, "photos": ["https://s3-media1.fl.yelpcdn.com/bphoto/HfXBi87gY7gih195TNBbJg/o.jpg", "https://s3-media3.fl.yelpcdn.com/bphoto/GE3hiRy2O37hUbLXzMGA2A/o.jpg", "https://s3-media3.fl.yelpcdn.com/bphoto/pOtvRYKK4xV3nF32Vnyh8w/o.jpg"], "price": "$$", "hours": [{"open": [{"is_overnight": false, "start": "1600", "end": "0000", "day": 0}, {"is_overnight": false, "start": "1600", "end": "0000", "day": 1}, {"is_overnight": false, "start": "1600", "end": "0000", "day": 2}, {"is_overnight": false, "start": "1600", "end": "0000", "day": 3}, {"is_overnight": true, "start": "1600", "end": "0200", "day": 4}, {"is_overnight": true, "start": "1100", "end": "0200", "day": 5}, {"is_overnight": false, "start": "1100", "end": "2200", "day": 6}], "hours_type": "REGULAR", "is_open_now": false}], "transactions": []}, "a4K6WMS8JW31VBteDM5TIA": {"id": "a4K6WMS8JW31VBteDM5TIA", "alias": "manolin-seattle", "name": "Manolin", "image_url": "https://s3-media4.fl.yelpcdn.com/bphoto/f9KU-JOM0MkILzP053W8WQ/o.jpg", "is_claimed": true, "is_closed": false, "url": "https://www.yelp.com/biz/manolin-seattle?adjust_creative=6dT2LEKGFHkdpZhE3GbcSQ&utm_campaign=yelp_api_v3&utm_medium=api_v3_business_lookup&utm_source=6dT2LEKGFHkdpZhE3GbcSQ", "phone": "+12062943331", "display_phone": "(206) 294-3331", "review_count": 351, "categories": [{"alias": "seafood", "title": "Seafood"}], "rating": 4.5, "location": {"address1": "3621 Stone Way N", "address2": "", "address3": "", "city": "Seattle", "zip_code": "98103", "country": "US", "state": "WA", "display_address": ["3621 Stone Way N", "Seattle, WA 98103"], "cross_streets": "38th St & 36th St"}, "coordinates": {"latitude": 47.651215, "longitude": -122.343091}, "photos": ["https://s3-media4.fl.yelpcdn.com/bphoto/f9KU-JOM0MkILzP053W8WQ/o.jpg", "https://s3-media2.fl.yelpcdn.com/bphoto/Rc8nm6gwZkklp0gKmNTqlw/o.jpg", "https://s3-media4.fl.yelpcdn.com/bphoto/6lyoXHZGA4jCdZvEmNDHjQ/o.jpg"], "price": "$$", "hours": [{"open": [{"is_overnight": false, "start": "1600", "end": "2200", "day": 1}, {"is_overnight": false, "start": "1600", "end": "2200", "day": 2}, {"is_overnight": false, "start": "1600", "end": "2200", "day": 3}, {"is_overnight": false, "start": "1600", "end": "2200", "day": 4}, {"is_overnight": false, "start": "1600", "end": "2200", "day": 5}, {"is_overnight": false, "start": "1600", "end": "2100", "day": 6}], "hours_type": "REGULAR", "is_open_now": false}], "transactions": []}, "EjVi5qvVN-DC27ocfUhj0w": {"id": "EjVi5qvVN-DC27ocfUhj0w", "alias": "crow-seattle", "name": "Crow", "image_url": "https://s3-media1.fl.yelpcdn.com/bphoto/woD4GzR78vnhHAHqb3F1WA/o.jpg", "is_claimed": true, "is_closed": false, "url": "https://www.yelp.com/biz/crow-seattle?adjust_creative=6dT2LEKGFHkdpZhE3GbcSQ&utm_campaign=yelp_api_v3&utm_medium=api_v3_business_lookup&utm_source=6dT2LEKGFHkdpZhE3GbcSQ", "phone": "+12062838800", "display_phone": "(206) 283-8800", "review_count": 522, "categories": [{"alias": "newamerican", "title": "American (New)"}, {"alias": "wine_bars", "title": "Wine Bars"}, {"alias": "desserts", "title": "Desserts"}], "rating": 4.0, "location": {"address1": "823 5th Ave N", "address2": null, "address3": "", "city": "Seattle", "zip_code": "98109", "country": "US", "state": "WA", "display_address": ["823 5th Ave N", "Seattle, WA 98109"], "cross_streets": "Valley St & Aloha St"}, "coordinates": {"latitude": 47.62702, "longitude": -122.34783}, "photos": ["https://s3-media1.fl.yelpcdn.com/bphoto/woD4GzR78vnhHAHqb3F1WA/o.jpg", "https://s3-media1.fl.yelpcdn.com/bphoto/wsg621BlQXmBvZUbBF3YkQ/o.jpg", "https://s3-media2.fl.yelpcdn.com/bphoto/JNeGjUgK5jn9HX54zyZz_w/o.jpg"], "price": "$$", "hours": [{"open": [{"is_overnight": false, "start": "1630", "end": "2100", "day": 0}, {"is_overnight": false, "start": "1630", "end": "2100", "day": 1}, {"is_overnight": false, "start": "1630", "end": "2200", "day": 2}, {"is_overnight": false, "start": "1630", "end": "2200", "day": 3}, {"is_overnight": false, "start": "1630", "end": "2300", "day": 4}, {"is_overnight": false, "start": "1630", "end": "2300", "day": 5}, {"is_overnight": false, "start": "1630", "end": "2100", "day": 6}], "hours_type": "REGULAR", "is_open_now": false}], "transactions": []}, "7Oj8IKp1pibP4huWecsQ6A": {"id": "7Oj8IKp1pibP4huWecsQ6A", "alias": "quinns-seattle", "name": "Quinn's", "image_url": "https://s3-media2.fl.yelpcdn.com/bphoto/fN8cEHmZ4ZqocvFKFzRLGg/o.jpg", "is_claimed": true, "is_closed": false, "url": "https://www.yelp.com/biz/quinns-seattle?adjust_creative=6dT2LEKGFHkdpZhE3GbcSQ&utm_campaign=yelp_api_v3&utm_medium=api_v3_business_lookup&utm_source=6dT2LEKGFHkdpZhE3GbcSQ", "phone": "+12063257711", "display_phone": "(206) 325-7711", "review_count": 1251, "categories": [{"alias": "newamerican", "title": "American (New)"}, {"alias": "pubs", "title": "Pubs"}], "rating": 4.0, "location": {"address1": "1001 E Pike St", "address2": "", "address3": "", "city": "Seattle", "zip_code": "98122", "country": "US", "state": "WA", "display_address": ["1001 E Pike St", "Seattle, WA 98122"], "cross_streets": "11th Ave & 10th Ave"}, "coordinates": {"latitude": 47.61386, "longitude": -122.31922}, "photos": ["https://s3-media2.fl.yelpcdn.com/bphoto/fN8cEHmZ4ZqocvFKFzRLGg/o.jpg", "https://s3-media3.fl.yelpcdn.com/bphoto/Va6Z8zeQrOt_lgpFn86w8A/o.jpg", "https://s3-media3.fl.yelpcdn.com/bphoto/JzaOLkli0S2g3GTtFCCOcg/o.jpg"], "price": "$$", "hours": [{"open": [{"is_overnight": true, "start": "1500", "end": "0100", "day": 0}, {"is_overnight": true, "start": "1500", "end": "0100", "day": 1}, {"is_overnight": true, "start": "1500", "end": "0100", "day": 2}, {"is_overnight": true, "start": "1500", "end": "0100", "day": 3}, {"is_overnight": true, "start": "1500", "end": "0100", "day": 4}, {"is_overnight": true, "start": "1500", "end": "0100", "day": 5}, {"is_overnight": true, "start": "1500", "end": "0100", "day": 6}], "hours_type": "REGULAR", "is_open_now": false}], "transactions": []}, "43CI7FDQVks2blFrhXWesg": {"id": "43CI7FDQVks2blFrhXWesg", "alias": "herb-and-bitter-public-house-seattle", "name": "Herb & Bitter Public House", "image_url": "https://s3-media2.fl.yelpcdn.com/bphoto/mEPeyLz8GQjzDs4N6SrDXg/o.jpg", "is_claimed": true, "is_closed": false, "url": "https://www.yelp.com/biz/herb-and-bitter-public-house-seattle?adjust_creative=6dT2LEKGFHkdpZhE3GbcSQ&utm_campaign=yelp_api_v3&utm_medium=api_v3_business_lookup&utm_source=6dT2LEKGFHkdpZhE3GbcSQ", "phone": "+12067086468", "display_phone": "(206) 708-6468", "review_count": 250, "categories": [{"alias": "tapasmallplates", "title": "Tapas/Small Plates"}], "rating": 4.0, "location": {"address1": "516 Broadway E", "address2": "", "address3": "", "city": "Seattle", "zip_code": "98102", "country": "US", "state": "WA", "display_address": ["516 Broadway E", "Seattle, WA 98102"], "cross_streets": "Republican St & Mercer St"}, "coordinates": {"latitude": 47.6236055711029, "longitude": -122.320748173641}, "photos": ["https://s3-media2.fl.yelpcdn.com/bphoto/mEPeyLz8GQjzDs4N6SrDXg/o.jpg", "https://s3-media1.fl.yelpcdn.com/bphoto/ekqyEFnm4tQ_FKu0ITfYuA/o.jpg", "https://s3-media2.fl.yelpcdn.com/bphoto/8GE6MP0ONkwO5mjrT7jbMw/o.jpg"], "price": "$$", "hours": [{"open": [{"is_overnight": true, "start": "1600", "end": "0100", "day": 0}, {"is_overnight": true, "start": "1600", "end": "0100", "day": 1}, {"is_overnight": true, "start": "1600", "end": "0100", "day": 2}, {"is_overnight": true, "start": "1600", "end": "0100", "day": 3}, {"is_overnight": true, "start": "1600", "end": "0200", "day": 4}, {"is_overnight": true, "start": "1600", "end": "0200", "day": 5}, {"is_overnight": true, "start": "1600", "end": "0100", "day": 6}], "hours_type": "REGULAR", "is_open_now": false}], "transactions": ["restaurant_reservation"]}, "MyhLWqqSB-yKQWEM7ASKZQ": {"id": "MyhLWqqSB-yKQWEM7ASKZQ", "alias": "orfeo-seattle", "name": "Orfeo", "image_url": "https://s3-media3.fl.yelpcdn.com/bphoto/2OQ2vD6fgHuyK4XHozYo6Q/o.jpg", "is_claimed": true, "is_closed": false, "url": "https://www.yelp.com/biz/orfeo-seattle?adjust_creative=6dT2LEKGFHkdpZhE3GbcSQ&utm_campaign=yelp_api_v3&utm_medium=api_v3_business_lookup&utm_source=6dT2LEKGFHkdpZhE3GbcSQ", "phone": "+12064431972", "display_phone": "(206) 443-1972", "review_count": 312, "categories": [{"alias": "newamerican", "title": "American (New)"}, {"alias": "italian", "title": "Italian"}, {"alias": "pizza", "title": "Pizza"}], "rating": 4.0, "location": {"address1": "2107 3rd Ave", "address2": "", "address3": "", "city": "Seattle", "zip_code": "98121", "country": "US", "state": "WA", "display_address": ["2107 3rd Ave", "Seattle, WA 98121"], "cross_streets": "Lenora St & Blanchard St"}, "coordinates": {"latitude": 47.6131858825684, "longitude": -122.342834472656}, "photos": ["https://s3-media3.fl.yelpcdn.com/bphoto/2OQ2vD6fgHuyK4XHozYo6Q/o.jpg", "https://s3-media1.fl.yelpcdn.com/bphoto/6vkLA_rcDg5bTMqp5rcKaQ/o.jpg", "https://s3-media2.fl.yelpcdn.com/bphoto/myTSpBa9Lw2OEBVR2OXsUg/o.jpg"], "price": "$$", "hours": [{"open": [{"is_overnight": false, "start": "1600", "end": "2200", "day": 0}, {"is_overnight": false, "start": "1600", "end": "2200", "day": 1}, {"is_overnight": false, "start": "1600", "end": "2200", "day": 2}, {"is_overnight": false, "start": "1600", "end": "2200", "day": 3}, {"is_overnight": false, "start": "1600", "end": "2200", "day": 4}, {"is_overnight": false, "start": "1600", "end": "2200", "day": 5}, {"is_overnight": false, "start": "1600", "end": "2200", "day": 6}], "hours_type": "REGULAR", "is_open_now": false}], "transactions": ["restaurant_reservation"]}, "wxXMzqN0nXOMw9HYv2rhOQ": {"id": "wxXMzqN0nXOMw9HYv2rhOQ", "alias": "cook-weaver-seattle-2", "name": "Cook Weaver", "image_url": "https://s3-media4.fl.yelpcdn.com/bphoto/XqlMOeZIRtI96axw032OvA/o.jpg", "is_claimed": true, "is_closed": false, "url": "https://www.yelp.com/biz/cook-weaver-seattle-2?adjust_creative=6dT2LEKGFHkdpZhE3GbcSQ&utm_campaign=yelp_api_v3&utm_medium=api_v3_business_lookup&utm_source=6dT2LEKGFHkdpZhE3GbcSQ", "phone": "+12063240599", "display_phone": "(206) 324-0599", "review_count": 112, "categories": [{"alias": "modern_european", "title": "Modern European"}, {"alias": "cocktailbars", "title": "Cocktail Bars"}], "rating": 4.5, "location": {"address1": "806 E Roy St", "address2": "", "address3": null, "city": "Seattle", "zip_code": "98102", "country": "US", "state": "WA", "display_address": ["806 E Roy St", "Seattle, WA 98102"], "cross_streets": "E Harvard Ave & E Broadway"}, "coordinates": {"latitude": 47.62522, "longitude": -122.32172}, "photos": ["https://s3-media4.fl.yelpcdn.com/bphoto/XqlMOeZIRtI96axw032OvA/o.jpg", "https://s3-media3.fl.yelpcdn.com/bphoto/RiLjhsK9991fv5z6ddSlig/o.jpg", "https://s3-media2.fl.yelpcdn.com/bphoto/_SvEM5i53E-4H9l43cDEWQ/o.jpg"], "price": "$$", "hours": [{"open": [{"is_overnight": false, "start": "1500", "end": "2200", "day": 1}, {"is_overnight": false, "start": "1500", "end": "2200", "day": 2}, {"is_overnight": false, "start": "1500", "end": "2200", "day": 3}, {"is_overnight": false, "start": "1500", "end": "2200", "day": 4}, {"is_overnight": false, "start": "1500", "end": "2200", "day": 5}, {"is_overnight": false, "start": "1500", "end": "2200", "day": 6}], "hours_type": "REGULAR", "is_open_now": false}], "transactions": []}, "rgkwLKTmZdj72S1KmEkENg": {"id": "rgkwLKTmZdj72S1KmEkENg", "alias": "zig-zag-cafe-seattle-2", "name": "Zig Zag Cafe", "image_url": "https://s3-media1.fl.yelpcdn.com/bphoto/GkTDqQt2b81unM_i2T9zoA/o.jpg", "is_claimed": true, "is_closed": false, "url": "https://www.yelp.com/biz/zig-zag-cafe-seattle-2?adjust_creative=6dT2LEKGFHkdpZhE3GbcSQ&utm_campaign=yelp_api_v3&utm_medium=api_v3_business_lookup&utm_source=6dT2LEKGFHkdpZhE3GbcSQ", "phone": "+12066251146", "display_phone": "(206) 625-1146", "review_count": 902, "categories": [{"alias": "newamerican", "title": "American (New)"}, {"alias": "cocktailbars", "title": "Cocktail Bars"}, {"alias": "mediterranean", "title": "Mediterranean"}], "rating": 4.5, "location": {"address1": "1501 Western Ave", "address2": "Ste 202", "address3": "", "city": "Seattle", "zip_code": "98101", "country": "US", "state": "WA", "display_address": ["1501 Western Ave", "Ste 202", "Seattle, WA 98101"], "cross_streets": "Pike St"}, "coordinates": {"latitude": 47.6083803, "longitude": -122.3414779}, "photos": ["https://s3-media1.fl.yelpcdn.com/bphoto/GkTDqQt2b81unM_i2T9zoA/o.jpg", "https://s3-media2.fl.yelpcdn.com/bphoto/6C2Ud7d2dmx8MJirukkFLA/o.jpg", "https://s3-media3.fl.yelpcdn.com/bphoto/m2ZA0NNBzdKHpJdnxxB8GQ/o.jpg"], "price": "$$", "hours": [{"open": [{"is_overnight": true, "start": "1700", "end": "0200", "day": 0}, {"is_overnight": true, "start": "1700", "end": "0200", "day": 1}, {"is_overnight": true, "start": "1700", "end": "0200", "day": 2}, {"is_overnight": true, "start": "1700", "end": "0200", "day": 3}, {"is_overnight": true, "start": "1700", "end": "0200", "day": 4}, {"is_overnight": true, "start": "1700", "end": "0200", "day": 5}, {"is_overnight": true, "start": "1700", "end": "0200", "day": 6}], "hours_type": "REGULAR", "is_open_now": false}], "transactions": []}, "pFjKbQE5ildUhScdJyvBHg": {"id": "pFjKbQE5ildUhScdJyvBHg", "alias": "heartwood-provisions-seattle-3", "name": "Heartwood Provisions", "image_url": "https://s3-media2.fl.yelpcdn.com/bphoto/JDNCKFzbrkhIDqp0OVCHFw/o.jpg", "is_claimed": true, "is_closed": false, "url": "https://www.yelp.com/biz/heartwood-provisions-seattle-3?adjust_creative=6dT2LEKGFHkdpZhE3GbcSQ&utm_campaign=yelp_api_v3&utm_medium=api_v3_business_lookup&utm_source=6dT2LEKGFHkdpZhE3GbcSQ", "phone": "+12065823505", "display_phone": "(206) 582-3505", "review_count": 392, "categories": [{"alias": "newamerican", "title": "American (New)"}, {"alias": "desserts", "title": "Desserts"}, {"alias": "breakfast_brunch", "title": "Breakfast & Brunch"}], "rating": 4.5, "location": {"address1": "1103 1st Ave", "address2": null, "address3": "", "city": "Seattle", "zip_code": "98101", "country": "US", "state": "WA", "display_address": ["1103 1st Ave", "Seattle, WA 98101"], "cross_streets": "Seneca St & Spring St"}, "coordinates": {"latitude": 47.6054687, "longitude": -122.3369829}, "photos": ["https://s3-media2.fl.yelpcdn.com/bphoto/JDNCKFzbrkhIDqp0OVCHFw/o.jpg", "https://s3-media1.fl.yelpcdn.com/bphoto/gJR8xdsDcM8hTFs0758p1A/o.jpg", "https://s3-media2.fl.yelpcdn.com/bphoto/cA54MjO0D1j8TY0v9U_JHA/o.jpg"], "price": "$$$", "hours": [{"open": [{"is_overnight": false, "start": "1500", "end": "2200", "day": 0}, {"is_overnight": false, "start": "1500", "end": "2200", "day": 1}, {"is_overnight": false, "start": "1500", "end": "2200", "day": 2}, {"is_overnight": false, "start": "1500", "end": "2200", "day": 3}, {"is_overnight": false, "start": "1500", "end": "2300", "day": 4}, {"is_overnight": false, "start": "0930", "end": "1400", "day": 5}, {"is_overnight": false, "start": "1500", "end": "2300", "day": 5}, {"is_overnight": false, "start": "0930", "end": "1400", "day": 6}, {"is_overnight": false, "start": "1500", "end": "2200", "day": 6}], "hours_type": "REGULAR", "is_open_now": false}], "transactions": []}, "d6S_AgOYhWh3wWlCqP0_KQ": {"id": "d6S_AgOYhWh3wWlCqP0_KQ", "alias": "joule-seattle", "name": "Joule", "image_url": "https://s3-media4.fl.yelpcdn.com/bphoto/8U5_SO0nllvdYDduuZEQbg/o.jpg", "is_claimed": true, "is_closed": false, "url": "https://www.yelp.com/biz/joule-seattle?adjust_creative=6dT2LEKGFHkdpZhE3GbcSQ&utm_campaign=yelp_api_v3&utm_medium=api_v3_business_lookup&utm_source=6dT2LEKGFHkdpZhE3GbcSQ", "phone": "+12066325685", "display_phone": "(206) 632-5685", "review_count": 712, "categories": [{"alias": "asianfusion", "title": "Asian Fusion"}, {"alias": "korean", "title": "Korean"}, {"alias": "breakfast_brunch", "title": "Breakfast & Brunch"}], "rating": 4.0, "location": {"address1": "3506 Stone Way N", "address2": "", "address3": "", "city": "Seattle", "zip_code": "98103", "country": "US", "state": "WA", "display_address": ["3506 Stone Way N", "Seattle, WA 98103"], "cross_streets": "35th St & 36th St"}, "coordinates": {"latitude": 47.64962, "longitude": -122.3424}, "photos": ["https://s3-media4.fl.yelpcdn.com/bphoto/8U5_SO0nllvdYDduuZEQbg/o.jpg", "https://s3-media1.fl.yelpcdn.com/bphoto/LInCytyLXQ90F2lho3uy2A/o.jpg", "https://s3-media3.fl.yelpcdn.com/bphoto/Br32AoIYizqHDoe7z_FCjA/o.jpg"], "price": "$$", "hours": [{"open": [{"is_overnight": false, "start": "1700", "end": "2200", "day": 0}, {"is_overnight": false, "start": "1700", "end": "2200", "day": 1}, {"is_overnight": false, "start": "1700", "end": "2200", "day": 2}, {"is_overnight": false, "start": "1700", "end": "2200", "day": 3}, {"is_overnight": false, "start": "1700", "end": "2300", "day": 4}, {"is_overnight": false, "start": "1000", "end": "1400", "day": 5}, {"is_overnight": false, "start": "1700", "end": "2300", "day": 5}, {"is_overnight": false, "start": "1000", "end": "1400", "day": 6}, {"is_overnight": false, "start": "1700", "end": "2200", "day": 6}], "hours_type": "REGULAR", "is_open_now": false}], "transactions": []}, "xj-E9jNLiem7fcyUiaZd7A": {"id": "xj-E9jNLiem7fcyUiaZd7A", "alias": "bramling-cross-seattle-2", "name": "Bramling Cross", "image_url": "https://s3-media1.fl.yelpcdn.com/bphoto/o1dKeF0i4Os85aoeXrBJfg/o.jpg", "is_claimed": true, "is_closed": false, "url": "https://www.yelp.com/biz/bramling-cross-seattle-2?adjust_creative=6dT2LEKGFHkdpZhE3GbcSQ&utm_campaign=yelp_api_v3&utm_medium=api_v3_business_lookup&utm_source=6dT2LEKGFHkdpZhE3GbcSQ", "phone": "+12064208192", "display_phone": "(206) 420-8192", "review_count": 157, "categories": [{"alias": "gastropubs", "title": "Gastropubs"}], "rating": 4.0, "location": {"address1": "5205 Ballard Ave", "address2": "", "address3": "", "city": "Seattle", "zip_code": "98107", "country": "US", "state": "WA", "display_address": ["5205 Ballard Ave", "Seattle, WA 98107"], "cross_streets": "Vernon Pl & N 20th Ave"}, "coordinates": {"latitude": 47.6655235290527, "longitude": -122.382583618164}, "photos": ["https://s3-media1.fl.yelpcdn.com/bphoto/o1dKeF0i4Os85aoeXrBJfg/o.jpg", "https://s3-media2.fl.yelpcdn.com/bphoto/Zn94rype79NoKKyfq7uOkg/o.jpg", "https://s3-media3.fl.yelpcdn.com/bphoto/OuusJ441UWX5QsF_wkCe8A/o.jpg"], "price": "$$", "hours": [{"open": [{"is_overnight": false, "start": "1700", "end": "2200", "day": 0}, {"is_overnight": false, "start": "1700", "end": "2200", "day": 1}, {"is_overnight": false, "start": "1700", "end": "2200", "day": 2}, {"is_overnight": false, "start": "1700", "end": "2200", "day": 3}, {"is_overnight": false, "start": "1700", "end": "2300", "day": 4}, {"is_overnight": false, "start": "1700", "end": "2300", "day": 5}, {"is_overnight": false, "start": "1700", "end": "2200", "day": 6}], "hours_type": "REGULAR", "is_open_now": false}], "transactions": []}, "waY0VFsZX6c45i8hp8fNsw": {"id": "waY0VFsZX6c45i8hp8fNsw", "alias": "local-360-seattle-2", "name": "Local 360", "image_url": "https://s3-media4.fl.yelpcdn.com/bphoto/G4Vp8sYvjmDqYLezQ7y5og/o.jpg", "is_claimed": true, "is_closed": false, "url": "https://www.yelp.com/biz/local-360-seattle-2?adjust_creative=6dT2LEKGFHkdpZhE3GbcSQ&utm_campaign=yelp_api_v3&utm_medium=api_v3_business_lookup&utm_source=6dT2LEKGFHkdpZhE3GbcSQ", "phone": "+12064419360", "display_phone": "(206) 441-9360", "review_count": 2535, "categories": [{"alias": "newamerican", "title": "American (New)"}, {"alias": "breakfast_brunch", "title": "Breakfast & Brunch"}, {"alias": "bars", "title": "Bars"}], "rating": 4.0, "location": {"address1": "2234 1st Ave", "address2": "", "address3": "", "city": "Seattle", "zip_code": "98121", "country": "US", "state": "WA", "display_address": ["2234 1st Ave", "Seattle, WA 98121"], "cross_streets": "Bell St & Blanchard St"}, "coordinates": {"latitude": 47.61345, "longitude": -122.34609}, "photos": ["https://s3-media4.fl.yelpcdn.com/bphoto/G4Vp8sYvjmDqYLezQ7y5og/o.jpg", "https://s3-media1.fl.yelpcdn.com/bphoto/daNCWWDPbUNr564kC16oyA/o.jpg", "https://s3-media4.fl.yelpcdn.com/bphoto/gOGG-Wfn2A2pzQhXurW9CQ/o.jpg"], "price": "$$", "hours": [{"open": [{"is_overnight": false, "start": "1100", "end": "2100", "day": 0}, {"is_overnight": false, "start": "1100", "end": "2200", "day": 1}, {"is_overnight": false, "start": "1100", "end": "2200", "day": 2}, {"is_overnight": false, "start": "1100", "end": "2200", "day": 3}, {"is_overnight": false, "start": "1100", "end": "2200", "day": 4}, {"is_overnight": false, "start": "0900", "end": "2200", "day": 5}, {"is_overnight": false, "start": "0900", "end": "2100", "day": 6}], "hours_type": "REGULAR", "is_open_now": true}], "transactions": ["restaurant_reservation"]}, "_z_yU-duavPBAqHB64UpTA": {"id": "_z_yU-duavPBAqHB64UpTA", "alias": "ciudad-seattle-2", "name": "Ciudad", "image_url": "https://s3-media1.fl.yelpcdn.com/bphoto/YtMLAp-7QYxYqQ0jCs1JbQ/o.jpg", "is_claimed": true, "is_closed": false, "url": "https://www.yelp.com/biz/ciudad-seattle-2?adjust_creative=6dT2LEKGFHkdpZhE3GbcSQ&utm_campaign=yelp_api_v3&utm_medium=api_v3_business_lookup&utm_source=6dT2LEKGFHkdpZhE3GbcSQ", "phone": "+12067172984", "display_phone": "(206) 717-2984", "review_count": 130, "categories": [{"alias": "tapasmallplates", "title": "Tapas/Small Plates"}, {"alias": "bars", "title": "Bars"}], "rating": 4.5, "location": {"address1": "6118 12th Ave S", "address2": "", "address3": null, "city": "Seattle", "zip_code": "98108", "country": "US", "state": "WA", "display_address": ["6118 12th Ave S", "Seattle, WA 98108"], "cross_streets": "Bailey St & Harney St"}, "coordinates": {"latitude": 47.5481399, "longitude": -122.3169}, "photos": ["https://s3-media1.fl.yelpcdn.com/bphoto/YtMLAp-7QYxYqQ0jCs1JbQ/o.jpg", "https://s3-media1.fl.yelpcdn.com/bphoto/_3w17-yZjlGZrPXiNpRbpQ/o.jpg", "https://s3-media3.fl.yelpcdn.com/bphoto/my47oiA_A-aP_iJeLxvKsA/o.jpg"], "price": "$$", "hours": [{"open": [{"is_overnight": false, "start": "1100", "end": "2100", "day": 1}, {"is_overnight": false, "start": "1100", "end": "2100", "day": 2}, {"is_overnight": false, "start": "1100", "end": "2100", "day": 3}, {"is_overnight": false, "start": "1100", "end": "2200", "day": 4}, {"is_overnight": false, "start": "1100", "end": "2200", "day": 5}], "hours_type": "REGULAR", "is_open_now": true}], "transactions": []}, "UaszJCXczQ-djWsQ0ylVAA": {"id": "UaszJCXczQ-djWsQ0ylVAA", "alias": "damn-the-weather-seattle", "name": "Damn the Weather", "image_url": "https://s3-media2.fl.yelpcdn.com/bphoto/PwwO_oHEXrxzgq88eGGJ9g/o.jpg", "is_claimed": true, "is_closed": false, "url": "https://www.yelp.com/biz/damn-the-weather-seattle?adjust_creative=6dT2LEKGFHkdpZhE3GbcSQ&utm_campaign=yelp_api_v3&utm_medium=api_v3_business_lookup&utm_source=6dT2LEKGFHkdpZhE3GbcSQ", "phone": "+12069461283", "display_phone": "(206) 946-1283", "review_count": 340, "categories": [{"alias": "cocktailbars", "title": "Cocktail Bars"}, {"alias": "newamerican", "title": "American (New)"}, {"alias": "tapasmallplates", "title": "Tapas/Small Plates"}], "rating": 4.0, "location": {"address1": "116 1st Ave S", "address2": "", "address3": "", "city": "Seattle", "zip_code": "98104", "country": "US", "state": "WA", "display_address": ["116 1st Ave S", "Seattle, WA 98104"], "cross_streets": "Washington St & Yesler Way"}, "coordinates": {"latitude": 47.6011167, "longitude": -122.3340814}, "photos": ["https://s3-media2.fl.yelpcdn.com/bphoto/PwwO_oHEXrxzgq88eGGJ9g/o.jpg", "https://s3-media1.fl.yelpcdn.com/bphoto/_VVxwaPyEMNyfHpt9jYYhw/o.jpg", "https://s3-media1.fl.yelpcdn.com/bphoto/BL45dQSu0P_2HCWmIMdyZA/o.jpg"], "price": "$$", "hours": [{"open": [{"is_overnight": false, "start": "1100", "end": "2300", "day": 0}, {"is_overnight": false, "start": "1100", "end": "2300", "day": 1}, {"is_overnight": false, "start": "1100", "end": "2300", "day": 2}, {"is_overnight": false, "start": "1100", "end": "2300", "day": 3}, {"is_overnight": true, "start": "1100", "end": "0100", "day": 4}, {"is_overnight": true, "start": "1600", "end": "0100", "day": 5}, {"is_overnight": false, "start": "1600", "end": "2300", "day": 6}], "hours_type": "REGULAR", "is_open_now": true}], "transactions": []}, "qERtBPTw_lLv0fkxw3cRPw": {"id": "qERtBPTw_lLv0fkxw3cRPw", "alias": "nue-seattle", "name": "Nue", "image_url": "https://s3-media2.fl.yelpcdn.com/bphoto/X2m_4w6puswF898eSguzew/o.jpg", "is_claimed": true, "is_closed": false, "url": "https://www.yelp.com/biz/nue-seattle?adjust_creative=6dT2LEKGFHkdpZhE3GbcSQ&utm_campaign=yelp_api_v3&utm_medium=api_v3_business_lookup&utm_source=6dT2LEKGFHkdpZhE3GbcSQ", "phone": "+12062570312", "display_phone": "(206) 257-0312", "review_count": 510, "categories": [{"alias": "tapasmallplates", "title": "Tapas/Small Plates"}, {"alias": "cocktailbars", "title": "Cocktail Bars"}, {"alias": "breakfast_brunch", "title": "Breakfast & Brunch"}], "rating": 4.0, "location": {"address1": "1519 14th Ave", "address2": "", "address3": "", "city": "Seattle", "zip_code": "98122", "country": "US", "state": "WA", "display_address": ["1519 14th Ave", "Seattle, WA 98122"], "cross_streets": "Pike St & Madison St"}, "coordinates": {"latitude": 47.614434286952, "longitude": -122.314304038882}, "photos": ["https://s3-media2.fl.yelpcdn.com/bphoto/X2m_4w6puswF898eSguzew/o.jpg", "https://s3-media2.fl.yelpcdn.com/bphoto/oQ3ni8R8IMdpcHX06JV4RQ/o.jpg", "https://s3-media3.fl.yelpcdn.com/bphoto/-4aVs8XeNe5_2ordkRS58Q/o.jpg"], "price": "$$", "hours": [{"open": [{"is_overnight": false, "start": "1000", "end": "2300", "day": 0}, {"is_overnight": false, "start": "1000", "end": "2300", "day": 1}, {"is_overnight": false, "start": "1000", "end": "2300", "day": 2}, {"is_overnight": false, "start": "1000", "end": "2300", "day": 3}, {"is_overnight": false, "start": "1000", "end": "0000", "day": 4}, {"is_overnight": false, "start": "1000", "end": "0000", "day": 5}, {"is_overnight": false, "start": "1000", "end": "2200", "day": 6}], "hours_type": "REGULAR", "is_open_now": true}], "transactions": ["pickup", "restaurant_reservation", "delivery"]}, "67QmiVYdCbG4PRmF61A5bw": {"id": "67QmiVYdCbG4PRmF61A5bw", "alias": "il-corvo-pasta-seattle", "name": "Il Corvo Pasta", "image_url": "https://s3-media4.fl.yelpcdn.com/bphoto/hSlULB9cJ9xulzYDulwtYA/o.jpg", "is_claimed": true, "is_closed": false, "url": "https://www.yelp.com/biz/il-corvo-pasta-seattle?adjust_creative=6dT2LEKGFHkdpZhE3GbcSQ&utm_campaign=yelp_api_v3&utm_medium=api_v3_business_lookup&utm_source=6dT2LEKGFHkdpZhE3GbcSQ", "phone": "+12065380999", "display_phone": "(206) 538-0999", "review_count": 849, "categories": [{"alias": "italian", "title": "Italian"}, {"alias": "noodles", "title": "Noodles"}, {"alias": "pastashops", "title": "Pasta Shops"}], "rating": 4.5, "location": {"address1": "217 James St", "address2": "", "address3": "", "city": "Seattle", "zip_code": "98104", "country": "US", "state": "WA", "display_address": ["217 James St", "Seattle, WA 98104"], "cross_streets": "3rd Ave & 2nd Ave"}, "coordinates": {"latitude": 47.60244, "longitude": -122.33165}, "photos": ["https://s3-media4.fl.yelpcdn.com/bphoto/hSlULB9cJ9xulzYDulwtYA/o.jpg", "https://s3-media4.fl.yelpcdn.com/bphoto/nTPbWAbB2saMBXTxvx9ugg/o.jpg", "https://s3-media1.fl.yelpcdn.com/bphoto/5lon1Dkb7r1rbEf5z8qdow/o.jpg"], "price": "$$", "hours": [{"open": [{"is_overnight": false, "start": "1100", "end": "1500", "day": 0}, {"is_overnight": false, "start": "1100", "end": "1500", "day": 1}, {"is_overnight": false, "start": "1100", "end": "1500", "day": 2}, {"is_overnight": false, "start": "1100", "end": "1500", "day": 3}, {"is_overnight": false, "start": "1100", "end": "1500", "day": 4}], "hours_type": "REGULAR", "is_open_now": true}], "transactions": []}, "0SShWqXD6ta6PNttsAj_BQ": {"id": "0SShWqXD6ta6PNttsAj_BQ", "alias": "lec\u014dsho-seattle-2", "name": "Lec\u014dsho", "image_url": "https://s3-media4.fl.yelpcdn.com/bphoto/DN_S1fQX8AU3QGxbh9jgKQ/o.jpg", "is_claimed": true, "is_closed": false, "url": "https://www.yelp.com/biz/lec%C5%8Dsho-seattle-2?adjust_creative=6dT2LEKGFHkdpZhE3GbcSQ&utm_campaign=yelp_api_v3&utm_medium=api_v3_business_lookup&utm_source=6dT2LEKGFHkdpZhE3GbcSQ", "phone": "+12066232101", "display_phone": "(206) 623-2101", "review_count": 685, "categories": [{"alias": "newamerican", "title": "American (New)"}, {"alias": "bars", "title": "Bars"}, {"alias": "seafood", "title": "Seafood"}], "rating": 4.0, "location": {"address1": "89 University St", "address2": "", "address3": "", "city": "Seattle", "zip_code": "98101", "country": "US", "state": "WA", "display_address": ["89 University St", "Seattle, WA 98101"], "cross_streets": "Post Aly & Western Ave"}, "coordinates": {"latitude": 47.606474929346, "longitude": -122.3387322711}, "photos": ["https://s3-media4.fl.yelpcdn.com/bphoto/DN_S1fQX8AU3QGxbh9jgKQ/o.jpg", "https://s3-media2.fl.yelpcdn.com/bphoto/SAo-4m7jcP4c2PKLHFrXjQ/o.jpg", "https://s3-media4.fl.yelpcdn.com/bphoto/sNmknHMhUvsQk1uhLmWdfg/o.jpg"], "price": "$$", "hours": [{"open": [{"is_overnight": true, "start": "1100", "end": "0100", "day": 0}, {"is_overnight": true, "start": "1100", "end": "0100", "day": 1}, {"is_overnight": true, "start": "1100", "end": "0100", "day": 2}, {"is_overnight": true, "start": "1100", "end": "0100", "day": 3}, {"is_overnight": true, "start": "1100", "end": "0100", "day": 4}, {"is_overnight": true, "start": "1500", "end": "0100", "day": 5}, {"is_overnight": true, "start": "1500", "end": "0100", "day": 6}], "hours_type": "REGULAR", "is_open_now": true}], "transactions": []}, "nQPPzUaPIMeJdohOrrjmOQ": {"id": "nQPPzUaPIMeJdohOrrjmOQ", "alias": "junebaby-seattle", "name": "JuneBaby", "image_url": "https://s3-media2.fl.yelpcdn.com/bphoto/TvmncVclrYucnW9HqWBWOw/o.jpg", "is_claimed": true, "is_closed": false, "url": "https://www.yelp.com/biz/junebaby-seattle?adjust_creative=6dT2LEKGFHkdpZhE3GbcSQ&utm_campaign=yelp_api_v3&utm_medium=api_v3_business_lookup&utm_source=6dT2LEKGFHkdpZhE3GbcSQ", "phone": "+12062574470", "display_phone": "(206) 257-4470", "review_count": 172, "categories": [{"alias": "southern", "title": "Southern"}], "rating": 4.0, "location": {"address1": "2122 NE 65th St", "address2": null, "address3": "", "city": "Seattle", "zip_code": "98115", "country": "US", "state": "WA", "display_address": ["2122 NE 65th St", "Seattle, WA 98115"], "cross_streets": "N 21st Ave & N Ravenna Ave"}, "coordinates": {"latitude": 47.67591, "longitude": -122.3041}, "photos": ["https://s3-media2.fl.yelpcdn.com/bphoto/TvmncVclrYucnW9HqWBWOw/o.jpg", "https://s3-media3.fl.yelpcdn.com/bphoto/5BHqBwK66tU1AerMA9y6Qw/o.jpg", "https://s3-media2.fl.yelpcdn.com/bphoto/IyzxL5E9WloDm78OsBG9CQ/o.jpg"], "price": "$$", "hours": [{"open": [{"is_overnight": false, "start": "1700", "end": "2200", "day": 2}, {"is_overnight": false, "start": "1700", "end": "2200", "day": 3}, {"is_overnight": false, "start": "1700", "end": "2200", "day": 4}, {"is_overnight": false, "start": "1100", "end": "2200", "day": 5}, {"is_overnight": false, "start": "1100", "end": "2200", "day": 6}], "hours_type": "REGULAR", "is_open_now": false}], "transactions": []}, "RzOn1WEsHZ-vY5ZxyfOAkw": {"id": "RzOn1WEsHZ-vY5ZxyfOAkw", "alias": "pomodoro-seattle", "name": "Pomodoro", "image_url": "https://s3-media3.fl.yelpcdn.com/bphoto/1-hX50r27oEdeyrnqpJdMQ/o.jpg", "is_claimed": true, "is_closed": false, "url": "https://www.yelp.com/biz/pomodoro-seattle?adjust_creative=6dT2LEKGFHkdpZhE3GbcSQ&utm_campaign=yelp_api_v3&utm_medium=api_v3_business_lookup&utm_source=6dT2LEKGFHkdpZhE3GbcSQ", "phone": "+12063243160", "display_phone": "(206) 324-3160", "review_count": 324, "categories": [{"alias": "italian", "title": "Italian"}, {"alias": "spanish", "title": "Spanish"}, {"alias": "basque", "title": "Basque"}], "rating": 4.5, "location": {"address1": "2366 Eastlake Ave E", "address2": "Ste 101", "address3": "", "city": "Seattle", "zip_code": "98102", "country": "US", "state": "WA", "display_address": ["2366 Eastlake Ave E", "Ste 101", "Seattle, WA 98102"], "cross_streets": "Lynn St & Louisa St"}, "coordinates": {"latitude": 47.641699, "longitude": -122.325672}, "photos": ["https://s3-media3.fl.yelpcdn.com/bphoto/1-hX50r27oEdeyrnqpJdMQ/o.jpg", "https://s3-media1.fl.yelpcdn.com/bphoto/FWNyUO2uIOSa3dd0wIWFUA/o.jpg", "https://s3-media1.fl.yelpcdn.com/bphoto/KszNo8HTNNs9aTYjaAqouw/o.jpg"], "price": "$$", "hours": [{"open": [{"is_overnight": false, "start": "1730", "end": "2300", "day": 1}, {"is_overnight": false, "start": "1730", "end": "2300", "day": 2}, {"is_overnight": false, "start": "1730", "end": "2300", "day": 3}, {"is_overnight": true, "start": "1700", "end": "0030", "day": 4}, {"is_overnight": true, "start": "1700", "end": "0030", "day": 5}, {"is_overnight": false, "start": "1700", "end": "2200", "day": 6}], "hours_type": "REGULAR", "is_open_now": false}], "transactions": []}, "DB3t02xPMSHK4NmAi79VXw": {"id": "DB3t02xPMSHK4NmAi79VXw", "alias": "ittos-2-capitol-hill-seattle", "name": "Itto's - 2 Capitol Hill", "image_url": "https://s3-media1.fl.yelpcdn.com/bphoto/j8J6IAOcgImUVioH8sgZ1g/o.jpg", "is_claimed": true, "is_closed": false, "url": "https://www.yelp.com/biz/ittos-2-capitol-hill-seattle?adjust_creative=6dT2LEKGFHkdpZhE3GbcSQ&utm_campaign=yelp_api_v3&utm_medium=api_v3_business_lookup&utm_source=6dT2LEKGFHkdpZhE3GbcSQ", "phone": "+12063250470", "display_phone": "(206) 325-0470", "review_count": 42, "categories": [{"alias": "moroccan", "title": "Moroccan"}, {"alias": "spanish", "title": "Spanish"}, {"alias": "tapas", "title": "Tapas Bars"}], "rating": 4.5, "location": {"address1": "601 Summit Ave E", "address2": null, "address3": "", "city": "Seattle", "zip_code": "98102", "country": "US", "state": "WA", "display_address": ["601 Summit Ave E", "Seattle, WA 98102"], "cross_streets": "Roy St & Mercer St"}, "coordinates": {"latitude": 47.62445, "longitude": -122.32553}, "photos": ["https://s3-media1.fl.yelpcdn.com/bphoto/j8J6IAOcgImUVioH8sgZ1g/o.jpg", "https://s3-media2.fl.yelpcdn.com/bphoto/IA0LkrTvNb63D5kE_Xisww/o.jpg", "https://s3-media4.fl.yelpcdn.com/bphoto/rumLfBLO4T10FmgbmdJeKQ/o.jpg"], "price": "$$", "hours": [{"open": [{"is_overnight": false, "start": "1600", "end": "0000", "day": 0}, {"is_overnight": false, "start": "1600", "end": "0000", "day": 1}, {"is_overnight": false, "start": "1600", "end": "0000", "day": 2}, {"is_overnight": false, "start": "1600", "end": "0000", "day": 3}, {"is_overnight": true, "start": "1600", "end": "0100", "day": 4}, {"is_overnight": true, "start": "1600", "end": "0100", "day": 5}, {"is_overnight": false, "start": "1600", "end": "0000", "day": 6}], "hours_type": "REGULAR", "is_open_now": false}], "transactions": []}, "gB4EYJyfojVme3sle9xz-Q": {"id": "gB4EYJyfojVme3sle9xz-Q", "alias": "eve-fremont-seattle", "name": "Eve Fremont", "image_url": "https://s3-media2.fl.yelpcdn.com/bphoto/fKqXy6kJ1Ub-V-zaPwDoMg/o.jpg", "is_claimed": true, "is_closed": false, "url": "https://www.yelp.com/biz/eve-fremont-seattle?adjust_creative=6dT2LEKGFHkdpZhE3GbcSQ&utm_campaign=yelp_api_v3&utm_medium=api_v3_business_lookup&utm_source=6dT2LEKGFHkdpZhE3GbcSQ", "phone": "+12069007186", "display_phone": "(206) 900-7186", "review_count": 179, "categories": [{"alias": "newamerican", "title": "American (New)"}], "rating": 4.0, "location": {"address1": "704 N 34th St", "address2": "", "address3": "", "city": "Seattle", "zip_code": "98103", "country": "US", "state": "WA", "display_address": ["704 N 34th St", "Seattle, WA 98103"], "cross_streets": "N Aurora Ave & N Fremont Ave"}, "coordinates": {"latitude": 47.64972, "longitude": -122.34895}, "photos": ["https://s3-media2.fl.yelpcdn.com/bphoto/fKqXy6kJ1Ub-V-zaPwDoMg/o.jpg", "https://s3-media4.fl.yelpcdn.com/bphoto/tdvpetnRMdkLJLjcKOWEYg/o.jpg", "https://s3-media3.fl.yelpcdn.com/bphoto/CEN8X2otSrF-BaAEyEGozg/o.jpg"], "price": "$$", "hours": [{"open": [{"is_overnight": false, "start": "1100", "end": "2200", "day": 0}, {"is_overnight": false, "start": "1100", "end": "2200", "day": 1}, {"is_overnight": false, "start": "1100", "end": "2200", "day": 2}, {"is_overnight": false, "start": "1100", "end": "2200", "day": 3}, {"is_overnight": false, "start": "1100", "end": "2200", "day": 4}, {"is_overnight": false, "start": "1000", "end": "1500", "day": 5}, {"is_overnight": false, "start": "1700", "end": "2200", "day": 5}, {"is_overnight": false, "start": "1000", "end": "1500", "day": 6}], "hours_type": "REGULAR", "is_open_now": true}], "transactions": ["restaurant_reservation"]}, "NaGkRnNbLcJdI8cF8JE3hw": {"id": "NaGkRnNbLcJdI8cF8JE3hw", "alias": "tilikum-place-cafe-seattle-3", "name": "Tilikum Place Cafe", "image_url": "https://s3-media2.fl.yelpcdn.com/bphoto/M9PnlH68RFuTBF3NSEnTTw/o.jpg", "is_claimed": true, "is_closed": false, "url": "https://www.yelp.com/biz/tilikum-place-cafe-seattle-3?adjust_creative=6dT2LEKGFHkdpZhE3GbcSQ&utm_campaign=yelp_api_v3&utm_medium=api_v3_business_lookup&utm_source=6dT2LEKGFHkdpZhE3GbcSQ", "phone": "+12062824830", "display_phone": "(206) 282-4830", "review_count": 1525, "categories": [{"alias": "breakfast_brunch", "title": "Breakfast & Brunch"}, {"alias": "cafes", "title": "Cafes"}], "rating": 4.5, "location": {"address1": "407 Cedar St", "address2": "", "address3": "", "city": "Seattle", "zip_code": "98121", "country": "US", "state": "WA", "display_address": ["407 Cedar St", "Seattle, WA 98121"], "cross_streets": "4th Ave"}, "coordinates": {"latitude": 47.61787, "longitude": -122.34751}, "photos": ["https://s3-media2.fl.yelpcdn.com/bphoto/M9PnlH68RFuTBF3NSEnTTw/o.jpg", "https://s3-media1.fl.yelpcdn.com/bphoto/hOeAVVIHX4P1loVwTXwKGQ/o.jpg", "https://s3-media1.fl.yelpcdn.com/bphoto/qyyR4kE_VZBBsom9S8CA5A/o.jpg"], "price": "$$", "hours": [{"open": [{"is_overnight": false, "start": "1100", "end": "1500", "day": 0}, {"is_overnight": false, "start": "1700", "end": "2200", "day": 0}, {"is_overnight": false, "start": "1100", "end": "1500", "day": 1}, {"is_overnight": false, "start": "1700", "end": "2200", "day": 1}, {"is_overnight": false, "start": "1100", "end": "1500", "day": 2}, {"is_overnight": false, "start": "1700", "end": "2200", "day": 2}, {"is_overnight": false, "start": "1100", "end": "1500", "day": 3}, {"is_overnight": false, "start": "1700", "end": "2200", "day": 3}, {"is_overnight": false, "start": "1100", "end": "1500", "day": 4}, {"is_overnight": false, "start": "1700", "end": "2200", "day": 4}, {"is_overnight": false, "start": "0800", "end": "1500", "day": 5}, {"is_overnight": false, "start": "1700", "end": "2200", "day": 5}, {"is_overnight": false, "start": "0800", "end": "1500", "day": 6}, {"is_overnight": false, "start": "1700", "end": "2200", "day": 6}], "hours_type": "REGULAR", "is_open_now": true}], "transactions": []}, "pHmG74puAbpCxD8aQRNDKg": {"id": "pHmG74puAbpCxD8aQRNDKg", "alias": "the-carlile-room-seattle", "name": "The Carlile Room", "image_url": "https://s3-media2.fl.yelpcdn.com/bphoto/ozVulhVjQ_gFSjjXxqlvuw/o.jpg", "is_claimed": true, "is_closed": false, "url": "https://www.yelp.com/biz/the-carlile-room-seattle?adjust_creative=6dT2LEKGFHkdpZhE3GbcSQ&utm_campaign=yelp_api_v3&utm_medium=api_v3_business_lookup&utm_source=6dT2LEKGFHkdpZhE3GbcSQ", "phone": "+12069469720", "display_phone": "(206) 946-9720", "review_count": 338, "categories": [{"alias": "newamerican", "title": "American (New)"}, {"alias": "bars", "title": "Bars"}, {"alias": "breakfast_brunch", "title": "Breakfast & Brunch"}], "rating": 4.0, "location": {"address1": "820 Pine St", "address2": "", "address3": "", "city": "Seattle", "zip_code": "98101", "country": "US", "state": "WA", "display_address": ["820 Pine St", "Seattle, WA 98101"], "cross_streets": "9th Ave & 8th Ave"}, "coordinates": {"latitude": 47.6133203, "longitude": -122.332877}, "photos": ["https://s3-media2.fl.yelpcdn.com/bphoto/ozVulhVjQ_gFSjjXxqlvuw/o.jpg", "https://s3-media2.fl.yelpcdn.com/bphoto/vPApKoVICn44rsc5PL3h6g/o.jpg", "https://s3-media2.fl.yelpcdn.com/bphoto/2GB6Dg_1UfQut40GK9dEZg/o.jpg"], "price": "$$", "hours": [{"open": [{"is_overnight": false, "start": "1600", "end": "0000", "day": 0}, {"is_overnight": false, "start": "1600", "end": "0000", "day": 1}, {"is_overnight": false, "start": "1600", "end": "0000", "day": 2}, {"is_overnight": false, "start": "1600", "end": "0000", "day": 3}, {"is_overnight": false, "start": "1600", "end": "0000", "day": 4}, {"is_overnight": false, "start": "1000", "end": "0000", "day": 5}, {"is_overnight": false, "start": "1000", "end": "0000", "day": 6}], "hours_type": "REGULAR", "is_open_now": false}], "transactions": []}, "-ofDNmj8r_F875FiZr9G8w": {"id": "-ofDNmj8r_F875FiZr9G8w", "alias": "witness-seattle", "name": "Witness", "image_url": "https://s3-media3.fl.yelpcdn.com/bphoto/mxtfTRbu0_TTnS39whLxdg/o.jpg", "is_claimed": true, "is_closed": false, "url": "https://www.yelp.com/biz/witness-seattle?adjust_creative=6dT2LEKGFHkdpZhE3GbcSQ&utm_campaign=yelp_api_v3&utm_medium=api_v3_business_lookup&utm_source=6dT2LEKGFHkdpZhE3GbcSQ", "phone": "+12063290248", "display_phone": "(206) 329-0248", "review_count": 658, "categories": [{"alias": "southern", "title": "Southern"}, {"alias": "cocktailbars", "title": "Cocktail Bars"}], "rating": 4.5, "location": {"address1": "410 Broadway E", "address2": "", "address3": "", "city": "Seattle", "zip_code": "98102", "country": "US", "state": "WA", "display_address": ["410 Broadway E", "Seattle, WA 98102"], "cross_streets": "Republican St & Harrison St"}, "coordinates": {"latitude": 47.6225508133524, "longitude": -122.320680460381}, "photos": ["https://s3-media3.fl.yelpcdn.com/bphoto/mxtfTRbu0_TTnS39whLxdg/o.jpg", "https://s3-media2.fl.yelpcdn.com/bphoto/lGiHqFkoN4nVcZC3GyLWtA/o.jpg", "https://s3-media3.fl.yelpcdn.com/bphoto/dbdj0w0SA1BQ8fJBDs9Ksw/o.jpg"], "price": "$$", "hours": [{"open": [{"is_overnight": true, "start": "1600", "end": "0100", "day": 0}, {"is_overnight": true, "start": "1600", "end": "0100", "day": 1}, {"is_overnight": true, "start": "1600", "end": "0100", "day": 2}, {"is_overnight": true, "start": "1600", "end": "0100", "day": 3}, {"is_overnight": true, "start": "1600", "end": "0200", "day": 4}, {"is_overnight": true, "start": "0900", "end": "0200", "day": 5}, {"is_overnight": true, "start": "0900", "end": "0100", "day": 6}], "hours_type": "REGULAR", "is_open_now": false}], "transactions": []}, "018rYSHznjI1lzEU9PDavA": {"id": "018rYSHznjI1lzEU9PDavA", "alias": "mkt-seattle", "name": "mkt.", "image_url": "https://s3-media1.fl.yelpcdn.com/bphoto/noWPuQMyCi--QtF546BOhw/o.jpg", "is_claimed": true, "is_closed": false, "url": "https://www.yelp.com/biz/mkt-seattle?adjust_creative=6dT2LEKGFHkdpZhE3GbcSQ&utm_campaign=yelp_api_v3&utm_medium=api_v3_business_lookup&utm_source=6dT2LEKGFHkdpZhE3GbcSQ", "phone": "+12068121580", "display_phone": "(206) 812-1580", "review_count": 261, "categories": [{"alias": "newamerican", "title": "American (New)"}], "rating": 4.5, "location": {"address1": "2108 N 55th St", "address2": "", "address3": "", "city": "Seattle", "zip_code": "98103", "country": "US", "state": "WA", "display_address": ["2108 N 55th St", "Seattle, WA 98103"], "cross_streets": "56th St & N Kenwood Pl"}, "coordinates": {"latitude": 47.6686946, "longitude": -122.3329512}, "photos": ["https://s3-media1.fl.yelpcdn.com/bphoto/noWPuQMyCi--QtF546BOhw/o.jpg", "https://s3-media2.fl.yelpcdn.com/bphoto/6sAThzGRndTpKXS7XvdNvA/o.jpg", "https://s3-media4.fl.yelpcdn.com/bphoto/QJCBo5wFNiCNq1CH_XtREQ/o.jpg"], "price": "$$$", "hours": [{"open": [{"is_overnight": false, "start": "1700", "end": "2200", "day": 0}, {"is_overnight": false, "start": "1700", "end": "2200", "day": 1}, {"is_overnight": false, "start": "1700", "end": "2200", "day": 2}, {"is_overnight": false, "start": "1700", "end": "2200", "day": 3}, {"is_overnight": false, "start": "1700", "end": "2200", "day": 4}, {"is_overnight": false, "start": "1700", "end": "2200", "day": 5}, {"is_overnight": false, "start": "1700", "end": "2200", "day": 6}], "hours_type": "REGULAR", "is_open_now": false}], "transactions": []}, "TUZ8bJufEb_DmzvIOVVutA": {"id": "TUZ8bJufEb_DmzvIOVVutA", "alias": "super-six-seattle", "name": "Super Six", "image_url": "https://s3-media4.fl.yelpcdn.com/bphoto/almlZQMVZ97KV6EQukPIHA/o.jpg", "is_claimed": true, "is_closed": false, "url": "https://www.yelp.com/biz/super-six-seattle?adjust_creative=6dT2LEKGFHkdpZhE3GbcSQ&utm_campaign=yelp_api_v3&utm_medium=api_v3_business_lookup&utm_source=6dT2LEKGFHkdpZhE3GbcSQ", "phone": "+12064201201", "display_phone": "(206) 420-1201", "review_count": 382, "categories": [{"alias": "asianfusion", "title": "Asian Fusion"}, {"alias": "hawaiian", "title": "Hawaiian"}, {"alias": "newamerican", "title": "American (New)"}], "rating": 4.0, "location": {"address1": "3714 S Hudson St", "address2": "", "address3": "", "city": "Seattle", "zip_code": "98118", "country": "US", "state": "WA", "display_address": ["3714 S Hudson St", "Seattle, WA 98118"], "cross_streets": "S Rainier Ave & S 37th Ave"}, "coordinates": {"latitude": 47.55728, "longitude": -122.28556}, "photos": ["https://s3-media4.fl.yelpcdn.com/bphoto/almlZQMVZ97KV6EQukPIHA/o.jpg", "https://s3-media3.fl.yelpcdn.com/bphoto/twF6XmRytm1U6qacYVpN2g/o.jpg", "https://s3-media3.fl.yelpcdn.com/bphoto/rfxqySnC3_E90rgor5RGjQ/o.jpg"], "price": "$$", "hours": [{"open": [{"is_overnight": false, "start": "1100", "end": "2200", "day": 0}, {"is_overnight": false, "start": "1100", "end": "2200", "day": 1}, {"is_overnight": false, "start": "1100", "end": "2200", "day": 2}, {"is_overnight": false, "start": "1100", "end": "2200", "day": 3}, {"is_overnight": false, "start": "1100", "end": "2200", "day": 4}, {"is_overnight": false, "start": "0800", "end": "2200", "day": 5}, {"is_overnight": false, "start": "0800", "end": "2200", "day": 6}], "hours_type": "REGULAR", "is_open_now": true}], "transactions": []}, "IFzC8hzQpKNfVuJh84p1sw": {"id": "IFzC8hzQpKNfVuJh84p1sw", "alias": "copine-seattle", "name": "Copine", "image_url": "https://s3-media1.fl.yelpcdn.com/bphoto/H4NlozgAerDgp6QI2V04jg/o.jpg", "is_claimed": true, "is_closed": false, "url": "https://www.yelp.com/biz/copine-seattle?adjust_creative=6dT2LEKGFHkdpZhE3GbcSQ&utm_campaign=yelp_api_v3&utm_medium=api_v3_business_lookup&utm_source=6dT2LEKGFHkdpZhE3GbcSQ", "phone": "+12062582467", "display_phone": "(206) 258-2467", "review_count": 134, "categories": [{"alias": "newamerican", "title": "American (New)"}], "rating": 4.5, "location": {"address1": "6460 24th Ave NW", "address2": "", "address3": null, "city": "Seattle", "zip_code": "98107", "country": "US", "state": "WA", "display_address": ["6460 24th Ave NW", "Seattle, WA 98107"], "cross_streets": "64th St & 65th St"}, "coordinates": {"latitude": 47.6758391329994, "longitude": -122.387506788495}, "photos": ["https://s3-media1.fl.yelpcdn.com/bphoto/H4NlozgAerDgp6QI2V04jg/o.jpg", "https://s3-media2.fl.yelpcdn.com/bphoto/VKghfuoKNpsqNgHUDZkZpQ/o.jpg", "https://s3-media2.fl.yelpcdn.com/bphoto/0yL66gohSTzcxH5DhKeXEg/o.jpg"], "price": "$$$", "hours": [{"open": [{"is_overnight": false, "start": "1700", "end": "2100", "day": 1}, {"is_overnight": false, "start": "1700", "end": "2100", "day": 2}, {"is_overnight": false, "start": "1700", "end": "2100", "day": 3}, {"is_overnight": false, "start": "1700", "end": "2100", "day": 4}, {"is_overnight": false, "start": "1700", "end": "2100", "day": 5}], "hours_type": "REGULAR", "is_open_now": false}], "transactions": []}, "UzaMrsDMM7xmxtWLPTrmKw": {"id": "UzaMrsDMM7xmxtWLPTrmKw", "alias": "shaker-and-spear-seattle-2", "name": "Shaker and Spear", "image_url": "https://s3-media2.fl.yelpcdn.com/bphoto/R7Vufo0uEC2YCClJ_BP7-w/o.jpg", "is_claimed": true, "is_closed": false, "url": "https://www.yelp.com/biz/shaker-and-spear-seattle-2?adjust_creative=6dT2LEKGFHkdpZhE3GbcSQ&utm_campaign=yelp_api_v3&utm_medium=api_v3_business_lookup&utm_source=6dT2LEKGFHkdpZhE3GbcSQ", "phone": "+12068261700", "display_phone": "(206) 826-1700", "review_count": 400, "categories": [{"alias": "seafood", "title": "Seafood"}, {"alias": "newamerican", "title": "American (New)"}, {"alias": "breakfast_brunch", "title": "Breakfast & Brunch"}], "rating": 4.5, "location": {"address1": "2000 2nd Ave", "address2": null, "address3": null, "city": "Seattle", "zip_code": "98121", "country": "US", "state": "WA", "display_address": ["2000 2nd Ave", "Seattle, WA 98121"], "cross_streets": "Lenora St & Virginia St"}, "coordinates": {"latitude": 47.61203, "longitude": -122.34165}, "photos": ["https://s3-media2.fl.yelpcdn.com/bphoto/R7Vufo0uEC2YCClJ_BP7-w/o.jpg", "https://s3-media4.fl.yelpcdn.com/bphoto/_Migp3wPwHGBuPthQj5F4Q/o.jpg", "https://s3-media3.fl.yelpcdn.com/bphoto/45Vi4cDMdzIEp8b3P74-hg/o.jpg"], "price": "$$$", "hours": [{"open": [{"is_overnight": false, "start": "0700", "end": "1000", "day": 0}, {"is_overnight": false, "start": "1130", "end": "1430", "day": 0}, {"is_overnight": false, "start": "1700", "end": "2200", "day": 0}, {"is_overnight": false, "start": "0700", "end": "1000", "day": 1}, {"is_overnight": false, "start": "1130", "end": "1430", "day": 1}, {"is_overnight": false, "start": "1700", "end": "2200", "day": 1}, {"is_overnight": false, "start": "0700", "end": "1000", "day": 2}, {"is_overnight": false, "start": "1130", "end": "1430", "day": 2}, {"is_overnight": false, "start": "1700", "end": "2200", "day": 2}, {"is_overnight": false, "start": "0700", "end": "1000", "day": 3}, {"is_overnight": false, "start": "1130", "end": "1430", "day": 3}, {"is_overnight": false, "start": "1700", "end": "2200", "day": 3}, {"is_overnight": false, "start": "0700", "end": "1000", "day": 4}, {"is_overnight": false, "start": "1130", "end": "1430", "day": 4}, {"is_overnight": false, "start": "1700", "end": "2200", "day": 4}, {"is_overnight": false, "start": "0500", "end": "2200", "day": 5}, {"is_overnight": false, "start": "0500", "end": "2200", "day": 6}], "hours_type": "REGULAR", "is_open_now": false}], "transactions": []}, "OwOSuAvxoZpgS3KGkWr51w": {"id": "OwOSuAvxoZpgS3KGkWr51w", "alias": "how-to-cook-a-wolf-seattle", "name": "How To Cook a Wolf", "image_url": "https://s3-media2.fl.yelpcdn.com/bphoto/Caop9DmcxXxjTWzs7g5wOw/o.jpg", "is_claimed": true, "is_closed": false, "url": "https://www.yelp.com/biz/how-to-cook-a-wolf-seattle?adjust_creative=6dT2LEKGFHkdpZhE3GbcSQ&utm_campaign=yelp_api_v3&utm_medium=api_v3_business_lookup&utm_source=6dT2LEKGFHkdpZhE3GbcSQ", "phone": "+12068388090", "display_phone": "(206) 838-8090", "review_count": 793, "categories": [{"alias": "italian", "title": "Italian"}, {"alias": "tapasmallplates", "title": "Tapas/Small Plates"}], "rating": 4.0, "location": {"address1": "2208 Queen Anne Ave N", "address2": "", "address3": "", "city": "Seattle", "zip_code": "98109", "country": "US", "state": "WA", "display_address": ["2208 Queen Anne Ave N", "Seattle, WA 98109"], "cross_streets": "Mc Graw St & Boston St"}, "coordinates": {"latitude": 47.6385402665478, "longitude": -122.356887666769}, "photos": ["https://s3-media2.fl.yelpcdn.com/bphoto/Caop9DmcxXxjTWzs7g5wOw/o.jpg", "https://s3-media1.fl.yelpcdn.com/bphoto/T9kfubfZhI3mNl3WYH_L8A/o.jpg", "https://s3-media4.fl.yelpcdn.com/bphoto/cueM2F4flV-JySEhJ-q_wQ/o.jpg"], "price": "$$$", "hours": [{"open": [{"is_overnight": false, "start": "1700", "end": "2300", "day": 0}, {"is_overnight": false, "start": "1700", "end": "2300", "day": 1}, {"is_overnight": false, "start": "1700", "end": "2300", "day": 2}, {"is_overnight": false, "start": "1700", "end": "2300", "day": 3}, {"is_overnight": false, "start": "1700", "end": "2300", "day": 4}, {"is_overnight": false, "start": "1700", "end": "2300", "day": 5}, {"is_overnight": false, "start": "1700", "end": "2300", "day": 6}], "hours_type": "REGULAR", "is_open_now": false}], "transactions": []}, "Lw7NmZ3j-WEye97ywEmkXQ": {"id": "Lw7NmZ3j-WEye97ywEmkXQ", "alias": "vons-1000-spirits-seattle-4", "name": "Von's 1000 Spirits", "image_url": "https://s3-media2.fl.yelpcdn.com/bphoto/ClVy0w7zsSIPkrFAKCxSqA/o.jpg", "is_claimed": true, "is_closed": false, "url": "https://www.yelp.com/biz/vons-1000-spirits-seattle-4?adjust_creative=6dT2LEKGFHkdpZhE3GbcSQ&utm_campaign=yelp_api_v3&utm_medium=api_v3_business_lookup&utm_source=6dT2LEKGFHkdpZhE3GbcSQ", "phone": "+12066218667", "display_phone": "(206) 621-8667", "review_count": 951, "categories": [{"alias": "newamerican", "title": "American (New)"}, {"alias": "pizza", "title": "Pizza"}, {"alias": "gastropubs", "title": "Gastropubs"}], "rating": 4.0, "location": {"address1": "1225 1st Ave", "address2": "", "address3": "", "city": "Seattle", "zip_code": "98101", "country": "US", "state": "WA", "display_address": ["1225 1st Ave", "Seattle, WA 98101"], "cross_streets": "Seneca St & University St"}, "coordinates": {"latitude": 47.6067340675997, "longitude": -122.338306505391}, "photos": ["https://s3-media2.fl.yelpcdn.com/bphoto/ClVy0w7zsSIPkrFAKCxSqA/o.jpg", "https://s3-media3.fl.yelpcdn.com/bphoto/x2I-pyrjlrE3vDhAbVAI1g/o.jpg", "https://s3-media2.fl.yelpcdn.com/bphoto/wm8tUo-suvJLNNpJYe71EQ/o.jpg"], "price": "$$", "hours": [{"open": [{"is_overnight": false, "start": "1100", "end": "0000", "day": 0}, {"is_overnight": false, "start": "1100", "end": "0000", "day": 1}, {"is_overnight": false, "start": "1100", "end": "0000", "day": 2}, {"is_overnight": false, "start": "1100", "end": "0000", "day": 3}, {"is_overnight": true, "start": "1100", "end": "0100", "day": 4}, {"is_overnight": true, "start": "0900", "end": "0100", "day": 5}, {"is_overnight": false, "start": "1100", "end": "0000", "day": 6}], "hours_type": "REGULAR", "is_open_now": true}], "transactions": ["pickup", "restaurant_reservation"]}, "Ih8PcUyFGrEX2PKZfHqdWg": {"id": "Ih8PcUyFGrEX2PKZfHqdWg", "alias": "the-masonry-seattle", "name": "The Masonry", "image_url": "https://s3-media2.fl.yelpcdn.com/bphoto/cLFd5EE0XXwFNUmjEECvYw/o.jpg", "is_claimed": true, "is_closed": false, "url": "https://www.yelp.com/biz/the-masonry-seattle?adjust_creative=6dT2LEKGFHkdpZhE3GbcSQ&utm_campaign=yelp_api_v3&utm_medium=api_v3_business_lookup&utm_source=6dT2LEKGFHkdpZhE3GbcSQ", "phone": "+12064534375", "display_phone": "(206) 453-4375", "review_count": 285, "categories": [{"alias": "bars", "title": "Bars"}, {"alias": "pizza", "title": "Pizza"}], "rating": 4.0, "location": {"address1": "20 Roy St", "address2": "", "address3": "", "city": "Seattle", "zip_code": "98109", "country": "US", "state": "WA", "display_address": ["20 Roy St", "Seattle, WA 98109"], "cross_streets": "N Queen Anne Ave & N 1st Ave"}, "coordinates": {"latitude": 47.6257, "longitude": -122.35575}, "photos": ["https://s3-media2.fl.yelpcdn.com/bphoto/cLFd5EE0XXwFNUmjEECvYw/o.jpg", "https://s3-media2.fl.yelpcdn.com/bphoto/kR2IJ1-CsJlMn0INWcDkEg/o.jpg", "https://s3-media1.fl.yelpcdn.com/bphoto/jEvKmv4ASl_Jj8Ar2jPO-Q/o.jpg"], "price": "$$", "hours": [{"open": [{"is_overnight": false, "start": "1130", "end": "0000", "day": 0}, {"is_overnight": false, "start": "1130", "end": "0000", "day": 1}, {"is_overnight": false, "start": "1130", "end": "0000", "day": 2}, {"is_overnight": false, "start": "1130", "end": "0000", "day": 3}, {"is_overnight": false, "start": "1130", "end": "0000", "day": 4}, {"is_overnight": false, "start": "1130", "end": "0000", "day": 5}, {"is_overnight": false, "start": "1130", "end": "0000", "day": 6}], "hours_type": "REGULAR", "is_open_now": false}], "transactions": []}, "-FOAQv22SXtSBs7nptI3UA": {"id": "-FOAQv22SXtSBs7nptI3UA", "alias": "serious-pie-seattle", "name": "Serious Pie", "image_url": "https://s3-media1.fl.yelpcdn.com/bphoto/gp6dXIKMLtoaba4Qg2S-BQ/o.jpg", "is_claimed": true, "is_closed": false, "url": "https://www.yelp.com/biz/serious-pie-seattle?adjust_creative=6dT2LEKGFHkdpZhE3GbcSQ&utm_campaign=yelp_api_v3&utm_medium=api_v3_business_lookup&utm_source=6dT2LEKGFHkdpZhE3GbcSQ", "phone": "+12068387388", "display_phone": "(206) 838-7388", "review_count": 3621, "categories": [{"alias": "pizza", "title": "Pizza"}], "rating": 4.0, "location": {"address1": "316 Virginia St", "address2": null, "address3": "", "city": "Seattle", "zip_code": "98121", "country": "US", "state": "WA", "display_address": ["316 Virginia St", "Seattle, WA 98121"], "cross_streets": ""}, "coordinates": {"latitude": 47.61296, "longitude": -122.34047}, "photos": ["https://s3-media1.fl.yelpcdn.com/bphoto/gp6dXIKMLtoaba4Qg2S-BQ/o.jpg", "https://s3-media3.fl.yelpcdn.com/bphoto/dsfQGCcvyZI0vJ19ip_uew/o.jpg", "https://s3-media4.fl.yelpcdn.com/bphoto/tDX1qpePvQSj-km-xT-Ijg/o.jpg"], "price": "$$", "hours": [{"open": [{"is_overnight": false, "start": "1100", "end": "2300", "day": 0}, {"is_overnight": false, "start": "1100", "end": "2300", "day": 1}, {"is_overnight": false, "start": "1100", "end": "2300", "day": 2}, {"is_overnight": false, "start": "1100", "end": "2300", "day": 3}, {"is_overnight": false, "start": "1100", "end": "2300", "day": 4}, {"is_overnight": false, "start": "1100", "end": "2300", "day": 5}, {"is_overnight": false, "start": "1100", "end": "2300", "day": 6}], "hours_type": "REGULAR", "is_open_now": true}], "transactions": []}, "Dr9CxgdePozHGwU4beaYGQ": {"id": "Dr9CxgdePozHGwU4beaYGQ", "alias": "ittos-tapas-west-seattle-seattle", "name": "Itto's Tapas- West Seattle", "image_url": "https://s3-media4.fl.yelpcdn.com/bphoto/4xVoSlhcyyFU4yRykSMxOQ/o.jpg", "is_claimed": true, "is_closed": false, "url": "https://www.yelp.com/biz/ittos-tapas-west-seattle-seattle?adjust_creative=6dT2LEKGFHkdpZhE3GbcSQ&utm_campaign=yelp_api_v3&utm_medium=api_v3_business_lookup&utm_source=6dT2LEKGFHkdpZhE3GbcSQ", "phone": "+12069325039", "display_phone": "(206) 932-5039", "review_count": 178, "categories": [{"alias": "moroccan", "title": "Moroccan"}, {"alias": "tapas", "title": "Tapas Bars"}, {"alias": "spanish", "title": "Spanish"}], "rating": 4.5, "location": {"address1": "4160 California Ave SW", "address2": "", "address3": "", "city": "Seattle", "zip_code": "98126", "country": "US", "state": "WA", "display_address": ["4160 California Ave SW", "Seattle, WA 98126"], "cross_streets": ""}, "coordinates": {"latitude": 47.5648, "longitude": -122.38655}, "photos": ["https://s3-media4.fl.yelpcdn.com/bphoto/4xVoSlhcyyFU4yRykSMxOQ/o.jpg", "https://s3-media2.fl.yelpcdn.com/bphoto/eG_PTaxvK8Ua4UEbmifddw/o.jpg", "https://s3-media2.fl.yelpcdn.com/bphoto/gsSHaOyHq0F4URSDoAa07A/o.jpg"], "price": "$$", "hours": [{"open": [{"is_overnight": false, "start": "1600", "end": "0000", "day": 0}, {"is_overnight": false, "start": "1600", "end": "0000", "day": 1}, {"is_overnight": false, "start": "1600", "end": "0000", "day": 2}, {"is_overnight": false, "start": "1600", "end": "0000", "day": 3}, {"is_overnight": false, "start": "1600", "end": "0000", "day": 4}, {"is_overnight": false, "start": "1600", "end": "0000", "day": 5}, {"is_overnight": false, "start": "1600", "end": "0000", "day": 6}], "hours_type": "REGULAR", "is_open_now": false}], "transactions": []}, "SG5DrR107I8AYBDqNrfimw": {"id": "SG5DrR107I8AYBDqNrfimw", "alias": "no-anchor-seattle-3", "name": "No Anchor", "image_url": "https://s3-media4.fl.yelpcdn.com/bphoto/6ixykoEBoqsUuzAKOC7rAw/o.jpg", "is_claimed": true, "is_closed": false, "url": "https://www.yelp.com/biz/no-anchor-seattle-3?adjust_creative=6dT2LEKGFHkdpZhE3GbcSQ&utm_campaign=yelp_api_v3&utm_medium=api_v3_business_lookup&utm_source=6dT2LEKGFHkdpZhE3GbcSQ", "phone": "+12064482610", "display_phone": "(206) 448-2610", "review_count": 147, "categories": [{"alias": "beerbar", "title": "Beer Bar"}, {"alias": "newamerican", "title": "American (New)"}, {"alias": "gastropubs", "title": "Gastropubs"}], "rating": 4.5, "location": {"address1": "2505 2nd Ave", "address2": "Ste 105", "address3": null, "city": "Seattle", "zip_code": "98121", "country": "US", "state": "WA", "display_address": ["2505 2nd Ave", "Ste 105", "Seattle, WA 98121"], "cross_streets": "Wall St & Vine St"}, "coordinates": {"latitude": 47.615292215253, "longitude": -122.34843313694}, "photos": ["https://s3-media4.fl.yelpcdn.com/bphoto/6ixykoEBoqsUuzAKOC7rAw/o.jpg", "https://s3-media1.fl.yelpcdn.com/bphoto/TEJbmHYv23O-PVWC8ll9yQ/o.jpg", "https://s3-media3.fl.yelpcdn.com/bphoto/bA6gl7-c45ERcAL3Yg-CiA/o.jpg"], "price": "$$", "hours": [{"open": [{"is_overnight": true, "start": "1200", "end": "0100", "day": 0}, {"is_overnight": true, "start": "1200", "end": "0100", "day": 1}, {"is_overnight": true, "start": "1200", "end": "0100", "day": 2}, {"is_overnight": true, "start": "1200", "end": "0100", "day": 3}, {"is_overnight": true, "start": "1200", "end": "0100", "day": 4}, {"is_overnight": true, "start": "1100", "end": "0100", "day": 5}, {"is_overnight": false, "start": "1100", "end": "2300", "day": 6}], "hours_type": "REGULAR", "is_open_now": false}], "transactions": []}, "GkxyrbqO0FdEeFJG_PaTgg": {"id": "GkxyrbqO0FdEeFJG_PaTgg", "alias": "thackeray-seattle-2", "name": "Thackeray", "image_url": "https://s3-media2.fl.yelpcdn.com/bphoto/jy4NRS84-5hYsEPMMo4Cvw/o.jpg", "is_claimed": true, "is_closed": false, "url": "https://www.yelp.com/biz/thackeray-seattle-2?adjust_creative=6dT2LEKGFHkdpZhE3GbcSQ&utm_campaign=yelp_api_v3&utm_medium=api_v3_business_lookup&utm_source=6dT2LEKGFHkdpZhE3GbcSQ", "phone": "+12067378743", "display_phone": "(206) 737-8743", "review_count": 242, "categories": [{"alias": "bars", "title": "Bars"}, {"alias": "tradamerican", "title": "American (Traditional)"}], "rating": 4.0, "location": {"address1": "3400 Stone Way N", "address2": null, "address3": "", "city": "Seattle", "zip_code": "98103", "country": "US", "state": "WA", "display_address": ["3400 Stone Way N", "Seattle, WA 98103"], "cross_streets": "35th St & 34th St"}, "coordinates": {"latitude": 47.649216, "longitude": -122.342439}, "photos": ["https://s3-media2.fl.yelpcdn.com/bphoto/jy4NRS84-5hYsEPMMo4Cvw/o.jpg", "https://s3-media3.fl.yelpcdn.com/bphoto/vFvQGUWiHM804B1bf2kRpg/o.jpg", "https://s3-media1.fl.yelpcdn.com/bphoto/A43WNiyEyrrWcYWJOVhmfg/o.jpg"], "price": "$$", "hours": [{"open": [{"is_overnight": false, "start": "1130", "end": "2200", "day": 0}, {"is_overnight": false, "start": "1130", "end": "2200", "day": 1}, {"is_overnight": false, "start": "1130", "end": "2200", "day": 2}, {"is_overnight": false, "start": "1130", "end": "2200", "day": 3}, {"is_overnight": false, "start": "1130", "end": "2300", "day": 4}, {"is_overnight": false, "start": "0900", "end": "2300", "day": 5}, {"is_overnight": false, "start": "0900", "end": "2200", "day": 6}], "hours_type": "REGULAR", "is_open_now": false}], "transactions": []}, "JGHqF70JD9ytZt_EP3G0bA": {"id": "JGHqF70JD9ytZt_EP3G0bA", "alias": "poppy-seattle", "name": "Poppy", "image_url": "https://s3-media4.fl.yelpcdn.com/bphoto/GJDapWqZBxTGdi0SXEiIzA/o.jpg", "is_claimed": true, "is_closed": false, "url": "https://www.yelp.com/biz/poppy-seattle?adjust_creative=6dT2LEKGFHkdpZhE3GbcSQ&utm_campaign=yelp_api_v3&utm_medium=api_v3_business_lookup&utm_source=6dT2LEKGFHkdpZhE3GbcSQ", "phone": "+12063241108", "display_phone": "(206) 324-1108", "review_count": 1027, "categories": [{"alias": "newamerican", "title": "American (New)"}, {"alias": "tapasmallplates", "title": "Tapas/Small Plates"}], "rating": 4.0, "location": {"address1": "622 Broadway E", "address2": "", "address3": "", "city": "Seattle", "zip_code": "98102", "country": "US", "state": "WA", "display_address": ["622 Broadway E", "Seattle, WA 98102"], "cross_streets": "Mercer St & Roy St"}, "coordinates": {"latitude": 47.624984588834, "longitude": -122.32073759206}, "photos": ["https://s3-media4.fl.yelpcdn.com/bphoto/GJDapWqZBxTGdi0SXEiIzA/o.jpg", "https://s3-media3.fl.yelpcdn.com/bphoto/xZtHRfLCE5000_NsXw0pkg/o.jpg", "https://s3-media1.fl.yelpcdn.com/bphoto/JN7g14rBPDsZPq2wDV0StQ/o.jpg"], "price": "$$$", "hours": [{"open": [{"is_overnight": false, "start": "1700", "end": "2230", "day": 0}, {"is_overnight": false, "start": "1700", "end": "2230", "day": 1}, {"is_overnight": false, "start": "1700", "end": "2230", "day": 2}, {"is_overnight": false, "start": "1700", "end": "2230", "day": 3}, {"is_overnight": false, "start": "1700", "end": "2330", "day": 4}, {"is_overnight": false, "start": "1700", "end": "2330", "day": 5}, {"is_overnight": false, "start": "1700", "end": "2200", "day": 6}], "hours_type": "REGULAR", "is_open_now": false}], "transactions": []}, "sNzOsVvZlvSO_-sXs2MMHQ": {"id": "sNzOsVvZlvSO_-sXs2MMHQ", "alias": "red-cedar-and-sage-seattle", "name": "Red Cedar & Sage", "image_url": "https://s3-media4.fl.yelpcdn.com/bphoto/9wVq7IeHof8y5l-_37VF3A/o.jpg", "is_claimed": true, "is_closed": false, "url": "https://www.yelp.com/biz/red-cedar-and-sage-seattle?adjust_creative=6dT2LEKGFHkdpZhE3GbcSQ&utm_campaign=yelp_api_v3&utm_medium=api_v3_business_lookup&utm_source=6dT2LEKGFHkdpZhE3GbcSQ", "phone": "+12065380377", "display_phone": "(206) 538-0377", "review_count": 237, "categories": [{"alias": "newamerican", "title": "American (New)"}, {"alias": "breakfast_brunch", "title": "Breakfast & Brunch"}, {"alias": "cocktailbars", "title": "Cocktail Bars"}], "rating": 4.0, "location": {"address1": "1501 Pike Pl", "address2": "Ste 200", "address3": "", "city": "Seattle", "zip_code": "98101", "country": "US", "state": "WA", "display_address": ["1501 Pike Pl", "Ste 200", "Seattle, WA 98101"], "cross_streets": "Post Aly"}, "coordinates": {"latitude": 47.60871, "longitude": -122.34105}, "photos": ["https://s3-media4.fl.yelpcdn.com/bphoto/9wVq7IeHof8y5l-_37VF3A/o.jpg", "https://s3-media2.fl.yelpcdn.com/bphoto/2WkgVvTxaYJTeVOoysTk2w/o.jpg", "https://s3-media2.fl.yelpcdn.com/bphoto/tKLyvms2mByCS5mScnIXAg/o.jpg"], "price": "$$", "hours": [{"open": [{"is_overnight": false, "start": "1130", "end": "2000", "day": 1}, {"is_overnight": false, "start": "1130", "end": "2030", "day": 2}, {"is_overnight": false, "start": "1130", "end": "2030", "day": 3}, {"is_overnight": false, "start": "1130", "end": "2100", "day": 4}, {"is_overnight": false, "start": "1000", "end": "2100", "day": 5}, {"is_overnight": false, "start": "1000", "end": "1500", "day": 6}], "hours_type": "REGULAR", "is_open_now": false}], "transactions": ["restaurant_reservation"]}, "Y-OgQKqreMaajTUCPbLPKg": {"id": "Y-OgQKqreMaajTUCPbLPKg", "alias": "tsukushinbo-seattle", "name": "Tsukushinbo", "image_url": "https://s3-media1.fl.yelpcdn.com/bphoto/DZ-Qsai5udTplG9e1k2r2Q/o.jpg", "is_claimed": true, "is_closed": false, "url": "https://www.yelp.com/biz/tsukushinbo-seattle?adjust_creative=6dT2LEKGFHkdpZhE3GbcSQ&utm_campaign=yelp_api_v3&utm_medium=api_v3_business_lookup&utm_source=6dT2LEKGFHkdpZhE3GbcSQ", "phone": "+12064674004", "display_phone": "(206) 467-4004", "review_count": 697, "categories": [{"alias": "japanese", "title": "Japanese"}, {"alias": "sushi", "title": "Sushi Bars"}, {"alias": "seafood", "title": "Seafood"}], "rating": 4.0, "location": {"address1": "515 S Main St", "address2": "", "address3": "", "city": "Seattle", "zip_code": "98104", "country": "US", "state": "WA", "display_address": ["515 S Main St", "Seattle, WA 98104"], "cross_streets": "S 6th Ave & S 5th Ave"}, "coordinates": {"latitude": 47.59985, "longitude": -122.32681}, "photos": ["https://s3-media1.fl.yelpcdn.com/bphoto/DZ-Qsai5udTplG9e1k2r2Q/o.jpg", "https://s3-media1.fl.yelpcdn.com/bphoto/QWzVhGOX5BEsgRkZyRUVgg/o.jpg", "https://s3-media4.fl.yelpcdn.com/bphoto/1Q1ghyGbEmqcnCoY9UQGDA/o.jpg"], "price": "$$", "hours": [{"open": [{"is_overnight": false, "start": "1730", "end": "2200", "day": 0}, {"is_overnight": false, "start": "1200", "end": "1400", "day": 1}, {"is_overnight": false, "start": "1730", "end": "2200", "day": 1}, {"is_overnight": false, "start": "1200", "end": "1400", "day": 2}, {"is_overnight": false, "start": "1730", "end": "2200", "day": 2}, {"is_overnight": false, "start": "1200", "end": "1400", "day": 3}, {"is_overnight": false, "start": "1730", "end": "2200", "day": 3}, {"is_overnight": false, "start": "1200", "end": "1400", "day": 4}, {"is_overnight": false, "start": "1730", "end": "2300", "day": 4}, {"is_overnight": false, "start": "1730", "end": "2300", "day": 5}, {"is_overnight": false, "start": "1100", "end": "1500", "day": 6}], "hours_type": "REGULAR", "is_open_now": false}], "transactions": []}, "5hvXRsi_oep4ArIqKbeM_w": {"id": "5hvXRsi_oep4ArIqKbeM_w", "alias": "petra-mediterranean-bistro-seattle", "name": "Petra Mediterranean Bistro", "image_url": "https://s3-media2.fl.yelpcdn.com/bphoto/DfC-YGSpy0noNeS3xqDnSA/o.jpg", "is_claimed": true, "is_closed": false, "url": "https://www.yelp.com/biz/petra-mediterranean-bistro-seattle?adjust_creative=6dT2LEKGFHkdpZhE3GbcSQ&utm_campaign=yelp_api_v3&utm_medium=api_v3_business_lookup&utm_source=6dT2LEKGFHkdpZhE3GbcSQ", "phone": "+12067285389", "display_phone": "(206) 728-5389", "review_count": 875, "categories": [{"alias": "mediterranean", "title": "Mediterranean"}, {"alias": "mideastern", "title": "Middle Eastern"}, {"alias": "greek", "title": "Greek"}], "rating": 4.5, "location": {"address1": "2501 4th Ave", "address2": "", "address3": "", "city": "Seattle", "zip_code": "98121", "country": "US", "state": "WA", "display_address": ["2501 4th Ave", "Seattle, WA 98121"], "cross_streets": "Wall St & Vine St"}, "coordinates": {"latitude": 47.61669, "longitude": -122.34653}, "photos": ["https://s3-media2.fl.yelpcdn.com/bphoto/DfC-YGSpy0noNeS3xqDnSA/o.jpg", "https://s3-media1.fl.yelpcdn.com/bphoto/2PCvnahAtI9-5lQaB9u7ng/o.jpg", "https://s3-media3.fl.yelpcdn.com/bphoto/4pO5vS8OP3xGBhzdh9SvLg/o.jpg"], "price": "$$", "hours": [{"open": [{"is_overnight": false, "start": "1100", "end": "1430", "day": 0}, {"is_overnight": false, "start": "1630", "end": "2100", "day": 0}, {"is_overnight": false, "start": "1100", "end": "1430", "day": 1}, {"is_overnight": false, "start": "1630", "end": "2100", "day": 1}, {"is_overnight": false, "start": "1100", "end": "1430", "day": 2}, {"is_overnight": false, "start": "1630", "end": "2100", "day": 2}, {"is_overnight": false, "start": "1100", "end": "1430", "day": 3}, {"is_overnight": false, "start": "1630", "end": "2100", "day": 3}, {"is_overnight": false, "start": "1100", "end": "1430", "day": 4}, {"is_overnight": false, "start": "1630", "end": "2130", "day": 4}, {"is_overnight": false, "start": "1630", "end": "2130", "day": 5}], "hours_type": "REGULAR", "is_open_now": true}], "transactions": ["pickup", "restaurant_reservation", "delivery"]}, "-pa-22jT0ssGBiBaGQWiqA": {"id": "-pa-22jT0ssGBiBaGQWiqA", "alias": "the-harvest-vine-seattle", "name": "The Harvest Vine", "image_url": "https://s3-media2.fl.yelpcdn.com/bphoto/rXoL5BA0ClxujUrJ1qGmrw/o.jpg", "is_claimed": true, "is_closed": false, "url": "https://www.yelp.com/biz/the-harvest-vine-seattle?adjust_creative=6dT2LEKGFHkdpZhE3GbcSQ&utm_campaign=yelp_api_v3&utm_medium=api_v3_business_lookup&utm_source=6dT2LEKGFHkdpZhE3GbcSQ", "phone": "+12063209771", "display_phone": "(206) 320-9771", "review_count": 536, "categories": [{"alias": "tapas", "title": "Tapas Bars"}, {"alias": "spanish", "title": "Spanish"}, {"alias": "basque", "title": "Basque"}], "rating": 4.5, "location": {"address1": "2701 E Madison St", "address2": "", "address3": "", "city": "Seattle", "zip_code": "98112", "country": "US", "state": "WA", "display_address": ["2701 E Madison St", "Seattle, WA 98112"], "cross_streets": "E 27th Ave & Martin Luther King Jr Way"}, "coordinates": {"latitude": 47.62258, "longitude": -122.29725}, "photos": ["https://s3-media2.fl.yelpcdn.com/bphoto/rXoL5BA0ClxujUrJ1qGmrw/o.jpg", "https://s3-media2.fl.yelpcdn.com/bphoto/bGFtEKs1GA_iWkcN89D59A/o.jpg", "https://s3-media1.fl.yelpcdn.com/bphoto/8fwk-_DmYliIOi2rkK4hvA/o.jpg"], "price": "$$$", "hours": [{"open": [{"is_overnight": false, "start": "1700", "end": "2200", "day": 0}, {"is_overnight": false, "start": "1700", "end": "2200", "day": 1}, {"is_overnight": false, "start": "1700", "end": "2200", "day": 2}, {"is_overnight": false, "start": "1700", "end": "2200", "day": 3}, {"is_overnight": false, "start": "1700", "end": "2200", "day": 4}, {"is_overnight": false, "start": "1700", "end": "2200", "day": 5}, {"is_overnight": false, "start": "1700", "end": "2200", "day": 6}], "hours_type": "REGULAR", "is_open_now": false}], "transactions": []}, "1GYKkZm14lZZHdvFkAtSXw": {"id": "1GYKkZm14lZZHdvFkAtSXw", "alias": "intermezzo-carmine-seattle-2", "name": "Intermezzo Carmine", "image_url": "https://s3-media1.fl.yelpcdn.com/bphoto/FAr-Ht2IlmSWkquVyG0svA/o.jpg", "is_claimed": true, "is_closed": false, "url": "https://www.yelp.com/biz/intermezzo-carmine-seattle-2?adjust_creative=6dT2LEKGFHkdpZhE3GbcSQ&utm_campaign=yelp_api_v3&utm_medium=api_v3_business_lookup&utm_source=6dT2LEKGFHkdpZhE3GbcSQ", "phone": "+12065968940", "display_phone": "(206) 596-8940", "review_count": 184, "categories": [{"alias": "cocktailbars", "title": "Cocktail Bars"}, {"alias": "italian", "title": "Italian"}], "rating": 4.5, "location": {"address1": "409 1st Ave S", "address2": "", "address3": "", "city": "Seattle", "zip_code": "98104", "country": "US", "state": "WA", "display_address": ["409 1st Ave S", "Seattle, WA 98104"], "cross_streets": "King St & Jackson St"}, "coordinates": {"latitude": 47.5988331, "longitude": -122.3342651}, "photos": ["https://s3-media1.fl.yelpcdn.com/bphoto/FAr-Ht2IlmSWkquVyG0svA/o.jpg", "https://s3-media2.fl.yelpcdn.com/bphoto/NqZREoxSZQwioreKjFSbNQ/o.jpg", "https://s3-media3.fl.yelpcdn.com/bphoto/tCt3Sivh1IWLz0EdKrFcrA/o.jpg"], "price": "$$", "hours": [{"open": [{"is_overnight": false, "start": "1130", "end": "0000", "day": 0}, {"is_overnight": false, "start": "1130", "end": "0000", "day": 1}, {"is_overnight": false, "start": "1130", "end": "0000", "day": 2}, {"is_overnight": false, "start": "1130", "end": "0000", "day": 3}, {"is_overnight": true, "start": "1130", "end": "0100", "day": 4}, {"is_overnight": true, "start": "1630", "end": "0100", "day": 5}], "hours_type": "REGULAR", "is_open_now": false}], "transactions": []}, "gamLTtrQNyjvaEPL6p6OVQ": {"id": "gamLTtrQNyjvaEPL6p6OVQ", "alias": "palace-kitchen-seattle", "name": "Palace Kitchen", "image_url": "https://s3-media2.fl.yelpcdn.com/bphoto/-fcrXXVXKa6gPFgxE80Zgg/o.jpg", "is_claimed": true, "is_closed": false, "url": "https://www.yelp.com/biz/palace-kitchen-seattle?adjust_creative=6dT2LEKGFHkdpZhE3GbcSQ&utm_campaign=yelp_api_v3&utm_medium=api_v3_business_lookup&utm_source=6dT2LEKGFHkdpZhE3GbcSQ", "phone": "+12064482001", "display_phone": "(206) 448-2001", "review_count": 1010, "categories": [{"alias": "newamerican", "title": "American (New)"}, {"alias": "bars", "title": "Bars"}, {"alias": "desserts", "title": "Desserts"}], "rating": 4.0, "location": {"address1": "2030 5th Ave", "address2": "", "address3": "", "city": "Seattle", "zip_code": "98121", "country": "US", "state": "WA", "display_address": ["2030 5th Ave", "Seattle, WA 98121"], "cross_streets": "Virginia St & Lenora St"}, "coordinates": {"latitude": 47.6145858764648, "longitude": -122.340019226074}, "photos": ["https://s3-media2.fl.yelpcdn.com/bphoto/-fcrXXVXKa6gPFgxE80Zgg/o.jpg", "https://s3-media4.fl.yelpcdn.com/bphoto/W_33dGMx8hIlj5yZkh1SVg/o.jpg", "https://s3-media3.fl.yelpcdn.com/bphoto/F1__yRolm_KUBe8b79MRiQ/o.jpg"], "price": "$$", "hours": [{"open": [{"is_overnight": true, "start": "1630", "end": "0100", "day": 0}, {"is_overnight": true, "start": "1630", "end": "0100", "day": 1}, {"is_overnight": true, "start": "1630", "end": "0100", "day": 2}, {"is_overnight": true, "start": "1630", "end": "0100", "day": 3}, {"is_overnight": true, "start": "1630", "end": "0100", "day": 4}, {"is_overnight": true, "start": "1700", "end": "0100", "day": 5}, {"is_overnight": true, "start": "1700", "end": "0100", "day": 6}], "hours_type": "REGULAR", "is_open_now": false}], "transactions": []}, "BKdSIJZ0YBaWM5YqOdNNkw": {"id": "BKdSIJZ0YBaWM5YqOdNNkw", "alias": "karaage-setsuna-seattle", "name": "Karaage Setsuna", "image_url": "https://s3-media3.fl.yelpcdn.com/bphoto/DU7Vfc6Cey7EVBsD-tX4Rw/o.jpg", "is_claimed": false, "is_closed": false, "url": "https://www.yelp.com/biz/karaage-setsuna-seattle?adjust_creative=6dT2LEKGFHkdpZhE3GbcSQ&utm_campaign=yelp_api_v3&utm_medium=api_v3_business_lookup&utm_source=6dT2LEKGFHkdpZhE3GbcSQ", "phone": "+12064483595", "display_phone": "(206) 448-3595", "review_count": 120, "categories": [{"alias": "japanese", "title": "Japanese"}, {"alias": "hawaiian", "title": "Hawaiian"}], "rating": 4.5, "location": {"address1": "2421 2nd Ave", "address2": "", "address3": null, "city": "Seattle", "zip_code": "98121", "country": "US", "state": "WA", "display_address": ["2421 2nd Ave", "Seattle, WA 98121"], "cross_streets": "Battery St & State Route 99"}, "coordinates": {"latitude": 47.61493, "longitude": -122.34756}, "photos": ["https://s3-media3.fl.yelpcdn.com/bphoto/DU7Vfc6Cey7EVBsD-tX4Rw/o.jpg", "https://s3-media1.fl.yelpcdn.com/bphoto/-ULT_UwoIcwqODzGLZ5jLA/o.jpg", "https://s3-media3.fl.yelpcdn.com/bphoto/hu713jf_AV7TltKxPKcpgg/o.jpg"], "price": "$$", "hours": [{"open": [{"is_overnight": false, "start": "1130", "end": "1400", "day": 0}, {"is_overnight": false, "start": "1700", "end": "2130", "day": 0}, {"is_overnight": false, "start": "1130", "end": "1400", "day": 1}, {"is_overnight": false, "start": "1700", "end": "2130", "day": 1}, {"is_overnight": false, "start": "1130", "end": "1400", "day": 2}, {"is_overnight": false, "start": "1700", "end": "2130", "day": 2}, {"is_overnight": false, "start": "1130", "end": "1400", "day": 3}, {"is_overnight": false, "start": "1700", "end": "2130", "day": 3}, {"is_overnight": false, "start": "1130", "end": "1400", "day": 4}, {"is_overnight": false, "start": "1700", "end": "2130", "day": 4}, {"is_overnight": false, "start": "1700", "end": "2130", "day": 5}], "hours_type": "REGULAR", "is_open_now": false}], "transactions": []}}